[{"id": "S95De3T8", "rated": true, "variant": "standard", "speed": "blitz", "perf": "blitz", "createdAt": 1777984408655, "lastMoveAt": 1777984745564, "status": "resign", "source": "arena", "players": {"white": {"user": {"name": "Play_More_and_WIN", "flair": "smileys.ghost", "id": "play_more_and_win"}, "rating": 1902, "ratingDiff": 8}, "black": {"user": {"name": "AdithyASreejitH", "flair": "smileys.alien", "id": "adithyasreejith"}, "rating": 2014, "ratingDiff": -15}}, "winner": "white", "opening": {"eco": "A45", "name": "Indian Defense: Accelerated London System", "ply": 3}, "moves": "d4 Nf6 Bf4 e6 e3 c5 c4 d5 Nc3 Nc6 Nf3 dxc4 Bxc4 Qb6 Qb3 cxd4 Qxb6 axb6 exd4 Bb4 O-O Bxc3 bxc3 O-O Ne5 Nxe5 Bxe5 Nd5 Bxd5 exd5 h3 Be6 f4 g6 g4 f5 g5 Rfc8 Rf3 Ra3 Rc1 Rxa2 h4 Ra3 Kf2 b5 Ke2 Ra2+ Kd1 Ra3 Kd2 Rc4 Rd3 Ra2+ Rc2 Ra1 Rc1 Rxc1 Kxc1 b4 Kb2 bxc3+ Rxc3 Rxc3 Kxc3 Bd7 Kb4 Kf7 Kc5 Ke6 Kb6 Bc6 Kc7 Ke7 Kb6 Kd7 Bg7 Kd6 Be5+ Kd7 Bb8 Kc8 Be5 Ba4 Kc5 b5 Kxd5 Bb3+ Kc6 Bc4 d5 Kd8 d6 Be6 Kxb5 Kd7 Kc5 Bb3 Kb6 Bd1 Kc5 Bf3 Kd4 Be4 Bg7 Bh1 Ke5 Bf3 Bf8 h5 Kf6 Kd8 Kxg6 Bg4 Kf6 Ke8 Be7 Kd7 g6", "clocks": [18003, 18003, 17787, 17867, 17731, 17699, 17715, 17651, 17403, 17547, 16859, 17299, 16747, 17155, 16059, 16339, 15779, 15947, 15723, 15819, 15587, 15339, 15587, 15235, 15523, 15051, 15523, 14691, 14571, 14691, 14171, 14595, 14043, 14395, 13859, 14243, 13779, 14115, 13387, 13955, 12331, 13707, 12003, 13179, 11811, 12875, 10891, 12563, 10379, 12395, 10259, 11667, 9331, 11043, 9219, 10931, 9075, 10755, 8899, 10667, 8851, 10571, 8851, 10427, 8851, 10355, 8787, 10307, 8683, 10227, 8347, 10139, 8211, 9883, 7443, 9779, 6971, 9323, 6859, 9147, 6651, 7675, 6379, 7331, 6091, 6787, 5803, 6411, 5307, 6291, 5227, 5955, 4859, 5843, 4723, 5699, 4507, 5563, 3995, 5387, 3947, 5339, 3867, 5243, 3675, 5027, 3451, 4307, 3187, 3675, 2907, 3299, 2835, 3299, 2763, 3203, 2643, 3099, 2602, 2911], "tournament": "e24JmPBr", "clock": {"initial": 180, "increment": 0, "totalTime": 180}}, {"id": "Y2nj0wUX", "rated": true, "variant": "standard", "speed": "blitz", "perf": "blitz", "createdAt": 1777645767576, "lastMoveAt": 1777645870450, "status": "resign", "source": "arena", "players": {"white": {"user": {"name": "HUBY_BHATTACHARYA", "id": "huby_bhattacharya"}, "rating": 2080, "ratingDiff": 5}, "black": {"user": {"name": "AdithyASreejitH", "flair": "smileys.alien", "id": "adithyasreejith"}, "rating": 2023, "ratingDiff": -9}}, "winner": "white", "opening": {"eco": "B23", "name": "Sicilian Defense: Grand Prix Attack", "ply": 5}, "moves": "e4 c5 Nc3 Nc6 f4 e6 Nf3 d5 Bb5 d4 Bxc6+ bxc6 Ne2 c4 d3 cxd3 cxd3 c5 O-O h5 b3 Be7 Qc2 Bb7 Ba3 Rc8 Rac1 Qa5 Qb2 Nf6 Rc2 Ng4 Rcc1 Ne3 Rf2 Ng4 Rff1 Ne3 Rfe1 h4 h3 Bd6 Nfxd4 cxd4 Bxd6 Kd7 Be5 Rxc1 Rxc1", "clocks": [18003, 9003, 17803, 8947, 17795, 8859, 17795, 8819, 17731, 8627, 17731, 8531, 17731, 8467, 17731, 8339, 17731, 8307, 17611, 8195, 17507, 8147, 17419, 8011, 17307, 7923, 17107, 7763, 16851, 7491, 15827, 7355, 15163, 7131, 14891, 6963, 14699, 6963, 14603, 6819, 14219, 6571, 13931, 6339, 13811, 5435, 13283, 4859, 13280, 4374], "tournament": "AHZdgj0X", "clock": {"initial": 180, "increment": 0, "totalTime": 180}}, {"id": "Q0CcPLSB", "rated": true, "variant": "standard", "speed": "blitz", "perf": "blitz", "createdAt": 1777641920953, "lastMoveAt": 1777641979436, "status": "resign", "source": "arena", "players": {"white": {"user": {"name": "Ghoderao1970", "id": "ghoderao1970"}, "rating": 1759, "ratingDiff": 9}, "black": {"user": {"name": "AdithyASreejitH", "flair": "smileys.alien", "id": "adithyasreejith"}, "rating": 2042, "ratingDiff": -19}}, "winner": "white", "opening": {"eco": "A02", "name": "Bird Opening: Schlechter Gambit", "ply": 4}, "moves": "f4 e5 fxe5 Nc6 d4 d6 exd6 Bxd6 Nf3 f6 e4 g5 c3 h5 Bd3 Qe7 O-O h4 e5 fxe5 Nxg5 exd4 Bg6+ Kd7 Rf7", "clocks": [18003, 9003, 17899, 8955, 17707, 8843, 17611, 8843, 17515, 8699, 17419, 8611, 17307, 8339, 16659, 7907, 16403, 7787, 16035, 7619, 15515, 7259, 15275, 6987, 15055, 6592], "tournament": "AHZdgj0X", "clock": {"initial": 180, "increment": 0, "totalTime": 180}}, {"id": "0xZhKPVX", "rated": true, "variant": "standard", "speed": "blitz", "perf": "blitz", "createdAt": 1777641753602, "lastMoveAt": 1777641890992, "status": "resign", "source": "arena", "players": {"white": {"user": {"name": "AdithyASreejitH", "flair": "smileys.alien", "id": "adithyasreejith"}, "rating": 2032, "ratingDiff": 10}, "black": {"user": {"name": "pman_fokus", "flair": "objects.crown", "id": "pman_fokus"}, "rating": 2003, "ratingDiff": -5}}, "winner": "white", "opening": {"eco": "B06", "name": "Modern Defense: Two Knights Variation", "ply": 7}, "moves": "d4 g6 Nf3 Bg7 Nc3 d6 e4 Nd7 Bf4 c6 Qd2 e5 dxe5 dxe5 Be3 Qe7 O-O-O Nb6 Bc5 Qc7 h3 Nd7 Bd6 Qa5 Bc4 Bh6 Ng5 Bxg5 Qxg5 Ngf6 f4 h6 Qg3 exf4 Bxf4 Nh5 Qf3 Nxf4 Qxf4 O-O Qxh6 Qb4 Qxg6+ Kh8 Qh6+ Kg8 Bb3 Ne5 Qg5+ Kh7 Qxe5 Be6 Bxe6 fxe6 Rd7+", "clocks": [9003, 9003, 9003, 8947, 8875, 8947, 8827, 8947, 8715, 8947, 8627, 8883, 8499, 8883, 8371, 8795, 8299, 8635, 7931, 8411, 7379, 7539, 7251, 7459, 6963, 7379, 6419, 7291, 6227, 6507, 5571, 6395, 5411, 6195, 5363, 5979, 5211, 5859, 5211, 5803, 5035, 5683, 4763, 5403, 4643, 5299, 4275, 4539, 3747, 3435, 3571, 3355, 3211, 3355, 3072, 2896], "tournament": "AHZdgj0X", "clock": {"initial": 180, "increment": 0, "totalTime": 180}}, {"id": "dBM34iu0", "rated": true, "variant": "standard", "speed": "blitz", "perf": "blitz", "createdAt": 1777376125217, "lastMoveAt": 1777376333353, "status": "outoftime", "source": "arena", "players": {"white": {"user": {"name": "Prathmesh0555", "id": "prathmesh0555"}, "rating": 2224, "ratingDiff": 3}, "black": {"user": {"name": "AdithyASreejitH", "flair": "smileys.alien", "id": "adithyasreejith"}, "rating": 2037, "ratingDiff": -5}}, "winner": "white", "opening": {"eco": "D37", "name": "Queen's Gambit Declined: Three Knights Variation", "ply": 7}, "moves": "Nf3 d5 d4 Nf6 c4 e6 Nc3 b6 g3 Bb7 Bg2 Bb4 O-O Bxc3 bxc3 Ne4 Qd3 Ba6 Ne5 Nd6 e4 Nxc4 Nxc4 Bxc4 Qf3 Bxf1 Kxf1 dxe4 Qxe4 c6 Ba3 Qd5 Qg4 Qc4+ Kg1 g6 Qf3 Nd7 Rc1 Qd5 Qd3 Qf5 Be4 Qf6 Bxc6 Rc8 d5 exd5 Qxd5 Qe6 Bxd7+ Qxd7 Re1+ Kd8 Be7+ Kc7 Qe5+ Kb7 Qe4+ Rc6 Bb4 Rc8 Qf3 Qc7 Re7 a5 Rxc7+ Rxc7 Bd6 Rd7 Be5 Re7 Bd4 Re6 Kg2 Ka6 Qd5 f6 a4 Kb7 Qb5 Kc7 c4 Red6 Be3 Re6 c5 Re5 cxb6+ Kb7 Qb3 Rec5 Qf7+ Kxb6 Qxh7 Ka6 Bxc5 Rxc5 Qxg6 Rc6 h4 Rb6 h5 Rc6 h6 Rb6 h7 Rc6 h8=Q Rb6 Qhxf6 Rxf6 Qxf6+", "clocks": [9003, 9003, 9003, 8979, 8987, 8779, 8931, 8715, 8931, 8675, 8931, 8499, 8931, 8419, 8843, 8419, 8731, 8131, 8139, 7411, 7291, 7283, 6643, 7067, 6643, 6755, 6643, 5955, 6643, 5955, 6419, 5187, 5883, 4195, 5803, 4043, 5315, 3331, 4803, 3155, 4635, 2915, 4203, 2739, 4003, 2699, 3883, 2523, 3883, 2395, 2763, 2315, 2763, 2235, 2723, 2139, 2675, 2091, 2555, 2051, 2339, 1899, 2147, 1691, 2027, 1691, 1939, 1643, 1867, 1483, 1779, 1403, 1659, 1323, 1539, 1283, 1483, 1227, 1363, 1035, 1307, 943, 1219, 899, 1075, 800, 1035, 800, 923, 752, 786, 649, 733, 538, 733, 326, 733, 318, 733, 303, 578, 303, 578, 236, 529, 236, 487, 236, 444, 236, 406, 44, 406, 0], "tournament": "2bUqeLM4", "clock": {"initial": 180, "increment": 0, "totalTime": 180}}, {"id": "ej6yLSTw", "rated": true, "variant": "standard", "speed": "blitz", "perf": "blitz", "createdAt": 1777375845776, "lastMoveAt": 1777376104458, "status": "mate", "source": "arena", "players": {"white": {"user": {"name": "dureja_arav", "flair": "smileys.alien", "id": "dureja_arav"}, "rating": 1281, "ratingDiff": -1}, "black": {"user": {"name": "AdithyASreejitH", "flair": "smileys.alien", "id": "adithyasreejith"}, "rating": 2037, "ratingDiff": 0}}, "winner": "black", "opening": {"eco": "C02", "name": "French Defense: Advance Variation, Nimzowitsch System", "ply": 7}, "moves": "e4 e6 d4 d5 e5 c5 Nf3 Nc6 Bb5 cxd4 Nxd4 Qb6 Bxc6+ bxc6 Be3 c5 Nb3 a5 c3 a4 N3d2 Qxb2 Na3 Qxa3 O-O Qxc3 Nf3 Qa5 Rc1 Ba6 Re1 d4 Bd2 Qc7 Qxa4+ Qd7 Qxd7+ Kxd7 Bf4 h6 Nd2 g5 Bg3 Ne7 Nb3 Nf5 Nxc5+ Bxc5 Rxc5 Nxg3 hxg3 Rac8 Ra5 Bb7 Ra7 Rc7 Rb1 Kc8 a4 Rd8 a5 d3 a6 Bxa6 Rxa6 d2 Rd1 Rc1 Ra8+ Kb7 Rxd8 Rxd1+ Kh2 Kc7 Rd3 Kc6 Kh3 h5 g4 h4 g3 Rh1+ Kg2 d1=Q Rxd1 Rxd1 Kh3 hxg3 Kxg3 Kd5 f4 Rd3+ Kf2 gxf4 Ke2 Rg3 Kf2 Rxg4 Kf3 Rh4 Kg2 Ke4 Kf2 Rh2+ Kg1 Re2 Kf1 Kf3 Kg1 Re1+ Kh2 Rf1 Kh3 Rh1#", "clocks": [18003, 9003, 17851, 9003, 17747, 8899, 17531, 8899, 17299, 8899, 17139, 8899, 16603, 8899, 16163, 8899, 15819, 8819, 15643, 8651, 15491, 8619, 14683, 8523, 14499, 8355, 13627, 7843, 13235, 7659, 13075, 7587, 12443, 7459, 12003, 7211, 11155, 7211, 10867, 6987, 10235, 6987, 10067, 6987, 9931, 6555, 9651, 6555, 9491, 6411, 9187, 6315, 8883, 6099, 8683, 5891, 8291, 5891, 7835, 5731, 7619, 5595, 7523, 5475, 7355, 5315, 7171, 5115, 6267, 4699, 6123, 4595, 5963, 4595, 5747, 4467, 5507, 4235, 5027, 4075, 4891, 3811, 4779, 3739, 4419, 3739, 4251, 3299, 4107, 3283, 3907, 3227, 3691, 3227, 3571, 2963, 3467, 2883, 3371, 2859, 3219, 2779, 3099, 2707, 3003, 2651, 2899, 2611, 2779, 2611, 2675, 2611, 2587, 2609], "tournament": "2bUqeLM4", "clock": {"initial": 180, "increment": 0, "totalTime": 180}}, {"id": "Yqcn3YJu", "rated": true, "variant": "standard", "speed": "blitz", "perf": "blitz", "createdAt": 1777375810896, "lastMoveAt": 1777375814946, "status": "resign", "source": "arena", "players": {"white": {"user": {"name": "AdithyASreejitH", "flair": "smileys.alien", "id": "adithyasreejith"}, "rating": 2037, "ratingDiff": 0}, "black": {"user": {"name": "Wladazgtr", "id": "wladazgtr"}, "rating": 883, "ratingDiff": 0}}, "winner": "white", "opening": {"eco": "A40", "name": "Queen's Pawn Game", "ply": 1}, "moves": "d4", "clocks": [9000, 18000], "tournament": "2bUqeLM4", "clock": {"initial": 180, "increment": 0, "totalTime": 180}}, {"id": "9SNyBT8Q", "rated": true, "variant": "standard", "speed": "blitz", "perf": "blitz", "createdAt": 1777375763546, "lastMoveAt": 1777375763546, "status": "noStart", "source": "arena", "players": {"white": {"user": {"name": "AdithyASreejitH", "flair": "smileys.alien", "id": "adithyasreejith"}, "rating": 2052, "ratingDiff": -15}, "black": {"user": {"name": "adiosamigos", "flair": "nature.four-leaf-clover", "id": "adiosamigos"}, "rating": 1956, "ratingDiff": 13}}, "winner": "black", "moves": "", "clocks": [18000], "tournament": "2bUqeLM4", "clock": {"initial": 180, "increment": 0, "totalTime": 180}}, {"id": "nZ6ZKJ6O", "rated": true, "variant": "standard", "speed": "blitz", "perf": "blitz", "createdAt": 1777267749574, "lastMoveAt": 1777268063167, "status": "mate", "source": "arena", "players": {"white": {"user": {"name": "AdithyASreejitH", "flair": "smileys.alien", "id": "adithyasreejith"}, "rating": 2058, "ratingDiff": -6}, "black": {"user": {"name": "LOTRNG", "flair": "smileys.ogre", "id": "lotrng"}, "rating": 2302, "ratingDiff": 2}}, "winner": "black", "opening": {"eco": "A41", "name": "Queen's Pawn Game", "ply": 2}, "moves": "d4 d6 Nf3 g6 e3 Bg7 Nc3 Nf6 Bd3 O-O e4 Nbd7 Bf4 Nh5 Be3 e5 d5 Nf4 Bxf4 exf4 Qd2 g5 h3 h6 O-O-O a6 g3 Ne5 Nxe5 Bxe5 Ne2 fxg3 fxg3 f5 exf5 Bxf5 Bxf5 Rxf5 Qd3 Qf6 h4 Bxb2+ Kb1 Rf3 hxg5 Rxd3 gxf6 Rxd1+ Rxd1 Bxf6 Nf4 Be5 Ne6 Rc8 Rh1 Kh7 Ng5+ Kg6 Ne6 c6 dxc6 bxc6 Rh4 Re8 Nf4+ Kg5 Rh5+ Kg4 Rxh6 Kxg3 Nd3 Rb8+ Kc1 Rc8 Nxe5 dxe5 Kd2 Kf4 Rf6+ Ke4 Rd6 a5 Kc3 Kf4 Kc4 e4 Kc5 e3 Kd4 Re8 Rf6+ Kg3 Rf1 e2 Re1 Kf2 Rxe2+ Kxe2 c4 Kd2 Kc5 Kc3 Kxc6 Kxc4 Kb6 Re5 Kc6 Kb4 Kd6 Rh5 Ke6 Ka3 Kf6 Kxa2 Kg6 Rb5 Kf6 Kb3 Ke6 Kc4 Kd6 a4 Kc6 a3 Kd6 a2 Kc6 a1=Q Kd6 Qa6+ Kc7 Rb7+ Kc8 Qa8#", "clocks": [18003, 18003, 17947, 17939, 17907, 17891, 17819, 17851, 17739, 17803, 17651, 17755, 17563, 17523, 17419, 17283, 17155, 17107, 17027, 16915, 17027, 16795, 16395, 16595, 16243, 16451, 16203, 16011, 15979, 15907, 15787, 13387, 15523, 13331, 15379, 13291, 15323, 13195, 15291, 12779, 15011, 12283, 14787, 12179, 13731, 11067, 13595, 11067, 13267, 11067, 13147, 10915, 12851, 10579, 12707, 10323, 12499, 10203, 12411, 9939, 11491, 9587, 11339, 8875, 11147, 8683, 10795, 8403, 10707, 7955, 10459, 7795, 10339, 5363, 9323, 5235, 9323, 5027, 9107, 4827, 8883, 4339, 8563, 3731, 8435, 3611, 8147, 3515, 7891, 2843, 7683, 2699, 7179, 2531, 7083, 2443, 7019, 2099, 6723, 1963, 6571, 1875, 6395, 1803, 6395, 1707, 6291, 1635, 6291, 1563, 6211, 1507, 6211, 1443, 6211, 1339, 6147, 1331, 6091, 1331, 6043, 1315, 6011, 1307, 5987, 1291, 5987, 1227, 5987, 1155, 5883, 1155, 5693, 1154], "tournament": "MUR4Kx9m", "clock": {"initial": 180, "increment": 0, "totalTime": 180}}, {"id": "eSdPP2mh", "rated": true, "variant": "standard", "speed": "blitz", "perf": "blitz", "createdAt": 1777267561383, "lastMoveAt": 1777267723368, "status": "mate", "source": "arena", "players": {"white": {"user": {"name": "BetrayedBySomeone", "flair": "symbols.broken-heart", "id": "betrayedbysomeone"}, "rating": 1992, "ratingDiff": -7}, "black": {"user": {"name": "AdithyASreejitH", "flair": "smileys.alien", "id": "adithyasreejith"}, "rating": 2045, "ratingDiff": 11}}, "winner": "black", "opening": {"eco": "B38", "name": "Sicilian Defense: Accelerated Dragon, Mar\u00f3czy Bind", "ply": 11}, "moves": "e4 c5 Nf3 Nc6 d4 cxd4 Nxd4 g6 c4 Bg7 Be3 Nf6 Nc3 d6 f3 O-O Qd2 Bd7 Be2 a6 O-O Rc8 Rac1 Qc7 b3 Qb8 Nxc6 Bxc6 Nd5 Bxd5 cxd5 b5 Rxc8 Rxc8 Rc1 Nd7 h3 Nb6 Bxb6 Rxc1+ Qxc1 Qxb6+ Kh1 Qb7 a4 bxa4 bxa4 h6 Qc6 Qb1+ Kh2 Be5+ g3 Qe1 Qxa6 Qxg3+ Kh1 Qh2#", "clocks": [9003, 9003, 8651, 8947, 8323, 8947, 8243, 8891, 7747, 8771, 7219, 8611, 7003, 8307, 6859, 8155, 6707, 8003, 6659, 7907, 6515, 7715, 6339, 7443, 5899, 7083, 4459, 6827, 4171, 6587, 4171, 6507, 3379, 6299, 3379, 6131, 3107, 5371, 2883, 5251, 2723, 5251, 2651, 4683, 2499, 4443, 2499, 4363, 2195, 3923, 2131, 3835, 2067, 3691, 1771, 3387, 1686, 3390], "tournament": "MUR4Kx9m", "clock": {"initial": 180, "increment": 0, "totalTime": 180}}, {"id": "OcXUxsmx", "rated": true, "variant": "standard", "speed": "blitz", "perf": "blitz", "createdAt": 1777096198092, "lastMoveAt": 1777096489467, "status": "mate", "source": "arena", "players": {"white": {"user": {"name": "Crewin83", "id": "crewin83"}, "rating": 1452, "ratingDiff": -9, "provisional": true}, "black": {"user": {"name": "AdithyASreejitH", "flair": "smileys.alien", "id": "adithyasreejith"}, "rating": 2045, "ratingDiff": 2}}, "winner": "black", "opening": {"eco": "B30", "name": "Sicilian Defense: Old Sicilian", "ply": 4}, "moves": "e4 c5 Nf3 Nc6 g3 e6 Bg2 d5 d3 Nf6 O-O dxe4 dxe4 Qxd1 Rxd1 Nxe4 Ne5 Nxe5 Bxe4 Nc6 Bxc6+ bxc6 Bf4 f6 Nc3 e5 Be3 Be6 Na4 c4 Bc5 Bxc5 Nxc5 Bd5 Rac1 Ke7 Na6 Rhd8 Nc7 Rac8 Nxd5+ cxd5 a4 d4 b3 c3 b4 Ke6 a5 Rc4 b5 Rb4 b6 axb6 a6 Ra4 Ra1 Rxa1 Rxa1 Ra8 a7 Kd5 Kf1 Kc6 Ke1 Kb7 Ke2 Rxa7 Rxa7+ Kxa7 Kd3 Ka6 Kc4 Ka5 Kb3 b5 f3 e4 fxe4 g6 h4 h5 Ka3 b4+ Kb3 Kb5 Ka2 Kc4 Kb1 d3 Kc1 d2+ Kd1 Kd4 e5 fxe5 Ke2 e4 Kf2 e3+ Ke2 Ke4 Kf1 d1=Q+ Kg2 Qe2+ Kh3 Qe1 Kh2 Kf3 Kh3 Qxg3#", "clocks": [18003, 9003, 17659, 8963, 17475, 8723, 17387, 8723, 16835, 8563, 16635, 8395, 16395, 8163, 16267, 8163, 15595, 6059, 14915, 6059, 14723, 6043, 14331, 5555, 14139, 5299, 13835, 5147, 13467, 4995, 13083, 4763, 12955, 4723, 11883, 4627, 11443, 3771, 11267, 3531, 10915, 3531, 10467, 3339, 10275, 3203, 9923, 3147, 9771, 3035, 9539, 2691, 9219, 2507, 9003, 2323, 8379, 2035, 8243, 2035, 8091, 1859, 7787, 1811, 7635, 1811, 6907, 1811, 6675, 1811, 6443, 1811, 6331, 1707, 6139, 1707, 5955, 1707, 5795, 1611, 5531, 1491, 4955, 1403, 4827, 1403, 4259, 1403, 4011, 1323, 3683, 1163, 3419, 1163, 3203, 1075, 2595, 1075, 2155, 1075, 2035, 1075, 1491, 1003, 1179, 1003, 1051, 1003, 533, 862, 381, 671], "tournament": "idrLOebA", "clock": {"initial": 180, "increment": 0, "totalTime": 180}}, {"id": "buhNVVKQ", "rated": true, "variant": "standard", "speed": "blitz", "perf": "blitz", "createdAt": 1776945410884, "lastMoveAt": 1776945589635, "status": "timeout", "source": "arena", "players": {"white": {"user": {"name": "AdithyASreejitH", "flair": "smileys.alien", "id": "adithyasreejith"}, "rating": 2062, "ratingDiff": -17}, "black": {"user": {"name": "SonJay2609", "flair": "activity.lichess-blitz", "id": "sonjay2609"}, "rating": 1940, "ratingDiff": 8}}, "winner": "black", "opening": {"eco": "D04", "name": "Queen's Pawn Game: Colle System, Anti-Colle", "ply": 6}, "moves": "d4 Nf6 Nf3 d5 e3 Bf5 c4 e6 Qb3 b6 Nc3 c6 Ne5 Bd6 f4 O-O Bd2 Ne4 Nxe4 Bxe4 Rc1 c5 dxc5 Bxc5 Bd3 Bxg2 Rg1 Qh4+ Kd1 Be4 Bxe4 dxe4 Rg2 Rd8 Kc2 f6 Ng4 Nc6 Bc3 Kf7 Rcg1 Rg8 Kb1 Rad8 Qc2 Rd3", "clocks": [18003, 18003, 17963, 17875, 17891, 17811, 17723, 17683, 17683, 17411, 17643, 17315, 17499, 16659, 17267, 16403, 17083, 15739, 16755, 15499, 16659, 15243, 16331, 15083, 16139, 14555, 16027, 14315, 15931, 12523, 15411, 12411, 14491, 11563, 14267, 10931, 13347, 10523, 13091, 10203, 12699, 9011, 12387, 8011, 12019, 7893, 9613], "tournament": "IC0Tyelo", "clock": {"initial": 180, "increment": 0, "totalTime": 180}}, {"id": "c945sbm9", "rated": true, "variant": "standard", "speed": "blitz", "perf": "blitz", "createdAt": 1776945242265, "lastMoveAt": 1776945375987, "status": "resign", "source": "arena", "players": {"white": {"user": {"name": "MakSha12", "flair": "people.brain", "id": "maksha12"}, "rating": 1839, "ratingDiff": -3}, "black": {"user": {"name": "AdithyASreejitH", "flair": "smileys.alien", "id": "adithyasreejith"}, "rating": 2056, "ratingDiff": 6}}, "winner": "black", "opening": {"eco": "B30", "name": "Sicilian Defense: Old Sicilian", "ply": 4}, "moves": "e4 c5 Nf3 Nc6 Nc3 e6 Bb5 d5 Bxc6+ bxc6 exd5 cxd5 d4 c4 O-O Bb4 Bd2 Nf6 Qe2 Bxc3 Bxc3 Ne4 Rfe1 Nxc3 bxc3 O-O Ne5 Qa5 Qe3 f6 Nc6 Qc7 Nb4 a5 Nd3 cxd3 Qxd3 Ba6 Qe3 Rfe8 Rab1 Rac8 f4 Qxc3 Qf2 Qxc2 Qh4 Qc4 f5 e5 dxe5 Qxh4", "clocks": [18003, 18003, 17715, 17947, 17579, 17723, 17523, 17635, 17443, 17491, 17387, 17483, 17179, 17323, 16315, 17211, 16227, 16963, 16083, 16835, 16083, 16731, 15899, 16555, 15843, 16459, 15635, 16115, 15395, 15891, 15211, 15427, 14995, 15291, 14651, 15099, 14651, 14899, 14459, 14419, 13907, 14291, 12555, 14051, 12043, 13867, 11931, 12979, 11635, 12683, 11483, 12513, 10798], "tournament": "IC0Tyelo", "clock": {"initial": 180, "increment": 0, "totalTime": 180}}, {"id": "frOMHzmK", "rated": true, "variant": "standard", "speed": "blitz", "perf": "blitz", "createdAt": 1776945124816, "lastMoveAt": 1776945211592, "status": "resign", "source": "arena", "players": {"white": {"user": {"name": "AdithyASreejitH", "flair": "smileys.alien", "id": "adithyasreejith"}, "rating": 2067, "ratingDiff": -11}, "black": {"user": {"name": "Quantum-pawnn", "id": "quantum-pawnn"}, "rating": 2144, "ratingDiff": 8}}, "winner": "black", "opening": {"eco": "D05", "name": "Rubinstein Opening", "ply": 9}, "moves": "d4 Nf6 Nf3 e6 e3 d5 Bd3 c5 b3 Nc6 a3 Bd6 Bb2 O-O Ne5 Bxe5 dxe5 Nd7 f4 f6 Qh5 f5 O-O Qe8 Qh4 Ne7 Rf3 Ng6 Qh5 Ngxe5 Qxe8 Nxf3+", "clocks": [18003, 18003, 17955, 17923, 17795, 17923, 17603, 17843, 17539, 17635, 17451, 17363, 17291, 17251, 17147, 16987, 16923, 16891, 16923, 16731, 16771, 16243, 16515, 15611, 16403, 15227, 16139, 15051, 15851, 14595, 15435, 14400, 15330], "tournament": "IC0Tyelo", "clock": {"initial": 180, "increment": 0, "totalTime": 180}}, {"id": "qV09SBn1", "rated": true, "variant": "standard", "speed": "blitz", "perf": "blitz", "createdAt": 1776944795186, "lastMoveAt": 1776945049533, "status": "outoftime", "source": "arena", "players": {"white": {"user": {"name": "jcfding", "flair": "smileys.skull-and-crossbones", "id": "jcfding"}, "rating": 2179, "ratingDiff": -8}, "black": {"user": {"name": "AdithyASreejitH", "flair": "smileys.alien", "id": "adithyasreejith"}, "rating": 2048, "ratingDiff": 19}}, "winner": "black", "opening": {"eco": "A45", "name": "Indian Defense: Accelerated London System", "ply": 3}, "moves": "d4 Nf6 Bf4 e6 e3 d6 Nf3 d5 Nbd2 c5 c3 Qb6 Rb1 Nc6 Bd3 c4 Bc2 Qa5 a3 b5 O-O Nh5 Bg5 h6 Bh4 Be7 e4 Nf6 Bg3 O-O e5 Nd7 Bh4 Bxh4 Nxh4 Qd8 g3 a5 f4 Bb7 f5 exf5 Nxf5 Qg5 h4 Qd8 Qg4 g6 Nd6 Ndxe5 dxe5 Nxe5 Nxb7 Qb6+ Qd4 Qxb7 Qxe5 Rae8 Qf4 Kg7 Qf6+ Kg8 Nf3 Re6 Qd4 Rfe8 Rf2 Qe7 Rbf1 Re2 Qxd5 Rxf2 Rxf2 Qe6 Qxb5 Qe1+", "clocks": [9003, 18003, 8923, 17939, 8835, 17883, 8707, 17843, 8347, 17795, 8243, 17739, 8115, 17619, 8043, 17475, 7931, 17339, 7803, 17147, 7571, 17027, 7075, 16843, 6979, 16283, 5675, 14371, 5123, 13667, 4947, 13467, 4531, 13243, 4531, 12491, 4243, 11923, 4099, 11459, 3883, 11339, 3763, 10875, 3667, 9779, 3363, 9387, 2611, 8835, 1923, 8787, 1859, 8379, 1691, 7683, 1603, 7619, 1539, 7179, 1323, 6643, 1171, 6499, 1035, 6371, 939, 6243, 776, 6083, 152, 5939, 152, 5739, 11, 5581, 0], "tournament": "IC0Tyelo", "clock": {"initial": 180, "increment": 0, "totalTime": 180}}, {"id": "WuezhVmm", "rated": true, "variant": "standard", "speed": "blitz", "perf": "blitz", "createdAt": 1776944084956, "lastMoveAt": 1776944375370, "status": "resign", "source": "arena", "players": {"white": {"user": {"name": "SonJay2609", "flair": "activity.lichess-blitz", "id": "sonjay2609"}, "rating": 1950, "ratingDiff": -4}, "black": {"user": {"name": "AdithyASreejitH", "flair": "smileys.alien", "id": "adithyasreejith"}, "rating": 2036, "ratingDiff": 12}}, "winner": "black", "opening": {"eco": "B30", "name": "Sicilian Defense: Old Sicilian", "ply": 4}, "moves": "e4 c5 Nf3 Nc6 c3 Nf6 e5 Nd5 d4 cxd4 cxd4 d6 Nc3 Nb6 Bb5 e6 O-O Bd7 exd6 Bxd6 Ne4 Be7 a3 O-O Bf4 a6 Bd3 f5 Nc3 g5 Be5 Nxe5 Nxe5 Be8 Ne2 Bf6 f4 gxf4 Rxf4 Nd5 Rf3 Qb6 Rg3+ Kh8 Rb1 Bxe5 Rh3 Bxd4+ Nxd4 Qxd4+ Kh1 Qf6 b4 Bg6 Qf3 Rad8 Re1 Nc3 Bc4 Ne4 Rh6 Qd4 Bxe6 Qd2 Rf1 Qxh6", "clocks": [18003, 18003, 17875, 17963, 17819, 17787, 17683, 17699, 17459, 17699, 17403, 17603, 17347, 17443, 17075, 17091, 16691, 16755, 16019, 16539, 15971, 15867, 15747, 15683, 15395, 15083, 15283, 14931, 13395, 14091, 13195, 13931, 12867, 13755, 11915, 13315, 11523, 13147, 10251, 12907, 9747, 11995, 8923, 11755, 7147, 10803, 6795, 10571, 6555, 10571, 6539, 10451, 5227, 10267, 5019, 9907, 4627, 9435, 4475, 9307, 2995, 8587, 2603, 8051, 2171, 7517, 1294], "tournament": "IC0Tyelo", "clock": {"initial": 180, "increment": 0, "totalTime": 180}}, {"id": "2RmDGGXD", "rated": true, "variant": "standard", "speed": "blitz", "perf": "blitz", "createdAt": 1776943795104, "lastMoveAt": 1776943941960, "status": "mate", "source": "arena", "players": {"white": {"user": {"name": "AdithyASreejitH", "flair": "smileys.alien", "id": "adithyasreejith"}, "rating": 2026, "ratingDiff": 10, "analysis": {"inaccuracy": 3, "mistake": 1, "blunder": 1, "acpl": 42}}, "black": {"user": {"name": "WK_or_MCFF", "flair": "symbols.vim-logo", "id": "wk_or_mcff"}, "rating": 1938, "ratingDiff": -4, "analysis": {"inaccuracy": 0, "mistake": 1, "blunder": 5, "acpl": 78}}}, "winner": "white", "opening": {"eco": "D11", "name": "Slav Defense: Quiet Variation, Pin Defense", "ply": 8}, "moves": "d4 d5 Nf3 Nf6 e3 Bg4 c4 c6 Nbd2 e6 Qb3 Qc7 Ne5 Bf5 Bd3 Bxd3 Qxd3 Bd6 f4 Nbd7 b3 dxc4 bxc4 c5 Bb2 cxd4 exd4 Rc8 O-O b5 c5 Bxe5 fxe5 Nd5 Ne4 O-O Nd6 Rb8 Rf3 g6 Qe4 a5 Rh3 Kg7 Qh4 h5 Qg5 Kh7 Rf1 a4 Bc1 Rh8 Rxf7+ Kg8 Qxg6#", "clocks": [9003, 18003, 8987, 17875, 8899, 17723, 8763, 17539, 8707, 17419, 8499, 17259, 8379, 17107, 8131, 16931, 8131, 16875, 7931, 16515, 7771, 16347, 7531, 16275, 7339, 16099, 7227, 15587, 7051, 15427, 6715, 14947, 6715, 14867, 5755, 14443, 5643, 14219, 5451, 13891, 5027, 13443, 4819, 13123, 4563, 12163, 4155, 11835, 3739, 11587, 3515, 11299, 3267, 11171, 3264], "analysis": [{"eval": 15}, {"eval": 27}, {"eval": 8}, {"eval": 11}, {"eval": 0}, {"eval": 35}, {"eval": 28}, {"eval": 30}, {"eval": 20}, {"eval": 22}, {"eval": 18}, {"eval": 37}, {"eval": 5}, {"eval": 4}, {"eval": -13}, {"eval": 3}, {"eval": 6}, {"eval": 0}, {"eval": -26}, {"eval": -22}, {"eval": -31}, {"eval": 17}, {"eval": 17}, {"eval": 28}, {"eval": 28}, {"eval": 28}, {"eval": 21}, {"eval": 23}, {"eval": 28}, {"eval": 190, "best": "e8h8", "variation": "O-O Qe2 Rfd8 Ndf3 h6 Rac1 b6", "judgment": {"name": "Mistake", "comment": "Mistake. O-O was best."}}, {"eval": 117, "best": "c4b5", "variation": "cxb5 O-O Rac1 Qb7 Ndc4 Bc7 Nc6 Nd5 Ba3 Rfe8 Qf3 a6", "judgment": {"name": "Inaccuracy", "comment": "Inaccuracy. cxb5 was best."}}, {"eval": 320, "best": "d6e7", "variation": "Be7 Ndf3 Nxe5 fxe5 Nd5 Qxb5+ Qd7 a4 Nc7 Qc4 Qd5 Qxd5", "judgment": {"name": "Blunder", "comment": "Blunder. Be7 was best."}}, {"eval": 319}, {"eval": 320}, {"eval": 344}, {"eval": 347}, {"eval": 207, "best": "e4g5", "variation": "Ng5 g6 Qh3 h5 Nxe6 Qb7 Nxf8 Nxf8 Qf3 Qd7 Rac1 Rc6", "judgment": {"name": "Mistake", "comment": "Mistake. Ng5 was best."}}, {"eval": 209}, {"eval": 120, "best": "d3h3", "variation": "Qh3 h6 Qg3 Qa5 Rf2 Ne7 Qh4 Nc6 Qh5 f5 Qg6", "judgment": {"name": "Inaccuracy", "comment": "Inaccuracy. Qh3 was best."}}, {"eval": 324, "best": "f7f6", "variation": "f6 Rh3 g6 Rg3 Nf4 Qe3 fxe5 h3 Nd5 Qh6 Rf4 Rc1", "judgment": {"name": "Blunder", "comment": "Blunder. f6 was best."}}, {"eval": 304}, {"eval": 309}, {"eval": 285}, {"eval": 323}, {"eval": 298}, {"eval": 315}, {"eval": 217, "best": "h3g3", "variation": "Rg3 Kh7 Qg5 Qd8 Nxf7 Qxg5 Nxg5+ Kg8 Nxe6 Rfe8 Ng5 b4", "judgment": {"name": "Inaccuracy", "comment": "Inaccuracy. Rg3 was best."}}, {"eval": 531, "best": "c7d8", "variation": "Qd8 Qd2 f5 exf6+ Qxf6 Re1 a4 Bc1 Qf4 Qxf4 Nxf4 Rg3", "judgment": {"name": "Blunder", "comment": "Blunder. Qd8 was best."}}, {"eval": 484}, {"mate": 6, "best": "d7c5", "variation": "Nxc5 dxc5 Qxc5+ Kh1 Qc2 Bc1 Kg8 Rhf3 b4 Nxf7 Rxf7 Rxf7", "judgment": {"name": "Blunder", "comment": "Checkmate is now unavoidable. Nxc5 was best."}}, {"eval": 523, "best": "d6f7", "variation": "Nxf7 Nf4 Rxf4 Qxe5 dxe5 Rxf7 Rxf7+ Kh8 Qh6+ Kg8 Qh7#", "judgment": {"name": "Blunder", "comment": "Lost forced checkmate sequence. Nxf7 was best."}}, {"mate": 2, "best": "d7e5", "variation": "Nxe5 dxe5 Kg8 Nxf7 Qxc5+ Kh1 Rxf7 Qxg6+ Rg7 Qxe6+ Kh8 Rxh5+", "judgment": {"name": "Blunder", "comment": "Checkmate is now unavoidable. Nxe5 was best."}}, {"mate": 1}, {"mate": 1}], "tournament": "IC0Tyelo", "clock": {"initial": 180, "increment": 0, "totalTime": 180}}, {"id": "p6c6Wrev", "rated": true, "variant": "standard", "speed": "blitz", "perf": "blitz", "createdAt": 1776943463774, "lastMoveAt": 1776943766948, "status": "outoftime", "source": "arena", "players": {"white": {"user": {"name": "The_SCFian_Boss", "flair": "nature.fire", "patron": true, "patronColor": 1, "id": "the_scfian_boss"}, "rating": 2020, "ratingDiff": -7}, "black": {"user": {"name": "AdithyASreejitH", "flair": "smileys.alien", "id": "adithyasreejith"}, "rating": 2009, "ratingDiff": 17}}, "winner": "black", "opening": {"eco": "A00", "name": "Hungarian Opening: Indian Defense", "ply": 2}, "moves": "g3 Nf6 Bg2 d5 Nf3 c6 O-O Nbd7 d4 g6 c3 Bg7 Re1 O-O Bf4 Nh5 Nbd2 Nxf4 gxf4 Qc7 e3 e6 Ne5 Nxe5 fxe5 Qd8 f4 f6 Nf3 f5 Ng5 h6 Nf3 g5 Qe2 g4 Nd2 Kh7 Qf2 Rg8 h3 Bf8 hxg4 Rxg4 Nf3 Be7 Nh2 Rg8 Kh1 Bh4 Qf3 Bxe1 Rxe1 Qf8 b3 Bd7 c4 Be8 cxd5 exd5 Qh3 Bd7 Nf3 Rg6 Rg1 Qe7 Ng5+ Kg7 Nf3 Rg8 Nh4 Rg4 Bf3 Rxg1+ Kxg1 Kh7+ Kf2 Qg7 Qh2 a5 a4 Be6 Bh5 Qe7 Kf3 Qb4 Bg6+ Rxg6 Nxg6 Kxg6 Qg2+ Kh7 Qg3 Qd2 Qh4 Qd1+ Kf2 Qc2+ Kf3 Qe4+ Kf2 Bf7 Qf6 Kg8 Qd8+ Kh7 Qf6 Qc2+ Kg3 Kg8 Qxh6 Qe2 Qg5+ Kf8 Qh6+ Ke8 Qh8+ Kd7 Qf6 Qg4+ Kf2 Qh5 Qd6+ Ke8 e6 Qh2+ Ke1 Qh4+ Kd2 Bxe6 Kc3 Qe7 Qb8+ Kf7 Qe5 Bd7 Qxf5+ Bxf5 e4 Qxe4 Kb2 Qd3 Ka3 Qc2 b4 Qc3+ Ka2 Qc4+ Kb2 Qxb4+ Kc1 Qxa4 Kd2 Qa1 Ke3 Qb2 Kf3 Qc3+ Kg2 Qd2+", "clocks": [9003, 18003, 9003, 17971, 8851, 17939, 8747, 17795, 8747, 17683, 8747, 17643, 8747, 17587, 8747, 17451, 8707, 17363, 8707, 17267, 8707, 17179, 8595, 17067, 8595, 16963, 8555, 16691, 8555, 16579, 8315, 16467, 8259, 16123, 8259, 16027, 8171, 15843, 8123, 15635, 8075, 15491, 7971, 15315, 7539, 15179, 7451, 14819, 7203, 14683, 7019, 14587, 6995, 14515, 6563, 14411, 6491, 14251, 6355, 13915, 6139, 13003, 6019, 12123, 5827, 11603, 5403, 11363, 5107, 10683, 4963, 10531, 4779, 10315, 4779, 10147, 4643, 9611, 4331, 9187, 4131, 8883, 3899, 7659, 2835, 7155, 2603, 6947, 2579, 6939, 2435, 6867, 2187, 6507, 2067, 6379, 2003, 6099, 1955, 5971, 1923, 5747, 1755, 5163, 1619, 4899, 1531, 4515, 1339, 4139, 1203, 3755, 1203, 3587, 1115, 3443, 1011, 3363, 978, 3187, 722, 3099, 524, 2971, 524, 2571, 397, 2259, 397, 2115, 397, 2003, 378, 1867, 378, 1779, 329, 1659, 329, 1603, 329, 1571, 329, 1547, 277, 1195, 277, 1067, 179, 1019, 179, 990, 177, 948, 177, 908, 169, 830, 72, 830, 0], "tournament": "IC0Tyelo", "clock": {"initial": 180, "increment": 0, "totalTime": 180}}, {"id": "izgWmHvU", "rated": true, "variant": "standard", "speed": "blitz", "perf": "blitz", "createdAt": 1776943136347, "lastMoveAt": 1776943353606, "status": "mate", "source": "arena", "players": {"white": {"user": {"name": "AdithyASreejitH", "flair": "smileys.alien", "id": "adithyasreejith"}, "rating": 1987, "ratingDiff": 22}, "black": {"user": {"name": "ankitganguly", "flair": "smileys.smiling-face-with-hearts", "id": "ankitganguly"}, "rating": 2135, "ratingDiff": -11}}, "winner": "white", "opening": {"eco": "D05", "name": "Rubinstein Opening", "ply": 9}, "moves": "d4 d5 Nf3 Nf6 e3 e6 Bd3 c5 b3 cxd4 exd4 Nc6 a3 Be7 Bb2 O-O Ne5 Nxe5 dxe5 Nd7 f4 f6 Qh5 f5 O-O Nc5 Rf3 Nxd3 cxd3 Qb6+ d4 Bd7 Rh3 h6 Qg6 Be8 Qg3 Kh7 Nd2 Rc8 Qd3 Bb5 Qe3 Rc2 Bc3 Rc8 Nb1 Qc6 a4 Ba6 b4 b5 axb5 Qxb5 Rf3 Bxb4 Bxb4 Rc1+ Kf2 Qxb4 Kg3 Rxb1 Rxa6 Qe1+ Qxe1 Rxe1 Rxa7 Rc4 Kh3 Rxd4 Rg3 Ree4 Raxg7+ Kh8 Rg8+ Kh7 R3g7#", "clocks": [18003, 9003, 17827, 9003, 17819, 8955, 17771, 8955, 17627, 8915, 17515, 8915, 17475, 8867, 17435, 8835, 17371, 8715, 17323, 8683, 17275, 8579, 17099, 7427, 16891, 7083, 16107, 6875, 15955, 6691, 15827, 5515, 15603, 5267, 15363, 4923, 15219, 4595, 15003, 4443, 13419, 4163, 12859, 4067, 12627, 3811, 12051, 2283, 11779, 2179, 11203, 2003, 11075, 2003, 10491, 1643, 9939, 1451, 9715, 1411, 9419, 1307, 9187, 1011, 8803, 1011, 8723, 921, 8611, 843, 8571, 815, 8227, 784, 8227, 784, 8071], "tournament": "IC0Tyelo", "clock": {"initial": 180, "increment": 0, "totalTime": 180}}, {"id": "SDWBQRzl", "rated": true, "variant": "standard", "speed": "blitz", "perf": "blitz", "createdAt": 1776345858455, "lastMoveAt": 1776346110348, "status": "draw", "source": "arena", "players": {"white": {"user": {"name": "AdithyASreejitH", "flair": "smileys.alien", "id": "adithyasreejith"}, "rating": 1992, "ratingDiff": -5}, "black": {"user": {"name": "rajahkazi", "id": "rajahkazi"}, "rating": 1876, "ratingDiff": 2}}, "opening": {"eco": "A40", "name": "Englund Gambit Declined: Reversed Alekhine", "ply": 3}, "moves": "d4 e5 Nf3 Bb4+ c3 Ba5 Nxe5 Nc6 Nxc6 dxc6 e4 Nf6 Bd3 Qe7 O-O O-O e5 Nd5 a3 b5 f4 f6 Qh5 g6 Qh6 fxe5 dxe5 Bf5 Bxf5 Rxf5 Qh3 Bb6+ Kh1 Raf8 g4 R5f7 f5 Qxe5 Bh6 Ne3 Nd2 Qd5+ Nf3 Nxf1 Bxf8 Rxf8 Rxf1 gxf5 gxf5 Qxf5 Qg2+ Kh8 Nd2 Qc8 Re1 Qe8 Rxe8 Rxe8 Nf1 Re1 Qf3 Kg7 Kg2 Rb1 Qxc6 Rxb2+ Kg3 Bf2+ Kf3 Bb6 Qd7+ Kg6 Qe6+ Kg7 h4 Rf2+ Kg4 Rxf1 h5 Rg1+ Kf5 Rf1+ Kg4 Rg1+ Kf5 Rf1+ Kg4", "clocks": [9003, 18003, 9003, 17467, 8867, 17011, 8707, 16627, 8547, 16483, 8515, 16275, 8467, 16059, 8371, 15843, 8187, 15667, 8083, 14971, 7523, 14579, 7179, 14331, 6899, 13259, 6667, 12795, 6403, 12691, 6355, 12123, 6227, 11955, 5867, 11443, 5755, 11027, 5403, 9515, 4531, 9051, 4299, 8731, 4011, 8539, 3867, 8355, 3667, 8235, 3331, 8051, 3291, 7179, 3051, 6539, 2755, 6395, 2651, 6203, 2587, 5755, 2323, 5523, 2211, 5355, 2211, 4963, 2099, 4691, 1979, 4523, 1907, 4403, 1715, 4019, 1691, 3851, 1691, 3683, 1691, 3243, 1691, 3107, 1635, 2979, 1637, 2976], "tournament": "ZaSEWF8o", "clock": {"initial": 180, "increment": 0, "totalTime": 180}}, {"id": "CW4n6Rtp", "rated": true, "variant": "standard", "speed": "blitz", "perf": "blitz", "createdAt": 1774510707454, "lastMoveAt": 1774510761821, "status": "timeout", "source": "arena", "players": {"white": {"user": {"name": "Sumathee", "id": "sumathee"}, "rating": 1975, "ratingDiff": 7}, "black": {"user": {"name": "AdithyASreejitH", "flair": "smileys.alien", "id": "adithyasreejith"}, "rating": 2007, "ratingDiff": -15}}, "winner": "white", "opening": {"eco": "A45", "name": "Indian Defense", "ply": 2}, "moves": "d4 Nf6 e3 e6 Bd3 d5 Nd2 c5 c3 Nc6 f4 cxd4 exd4 Bd6 Ne2 Nh5 Nf3 f5 O-O O-O Ne5 Nf6 Ng3", "clocks": [18003, 9003, 18003, 8955, 17859, 8835, 17803, 8683, 17763, 8427, 17707, 8043, 17603, 7915, 17547, 7683, 17379, 7035, 17091, 6923, 16971, 6243, 16687, 5030], "tournament": "7iaL35Fs", "clock": {"initial": 180, "increment": 0, "totalTime": 180}}, {"id": "1xCqrfgd", "rated": true, "variant": "standard", "speed": "blitz", "perf": "blitz", "createdAt": 1774510625402, "lastMoveAt": 1774510683441, "status": "resign", "source": "arena", "players": {"white": {"user": {"name": "AdithyASreejitH", "flair": "smileys.alien", "id": "adithyasreejith"}, "rating": 2022, "ratingDiff": -15}, "black": {"user": {"name": "Antonell", "id": "antonell"}, "rating": 1983, "ratingDiff": 6}}, "winner": "black", "opening": {"eco": "A48", "name": "Indian Defense: Colle System, King's Indian Variation", "ply": 8}, "moves": "d4 d6 Nf3 Nf6 e3 g6 Bd3 Bg7 Nbd2 O-O c4 c5 O-O cxd4 exd4 Nc6 Re1 e5 d5 Nb8 Qc2 Na6 a3 Nc5 Rb1 Nxd3 Qxd3 Bf5", "clocks": [9003, 18003, 8779, 17947, 8707, 17947, 8643, 17947, 8587, 17915, 8555, 17811, 8451, 17747, 8451, 17659, 8179, 17611, 7971, 17139, 7155, 16883, 7003, 16763, 6435, 16467, 6387, 16284, 6194], "tournament": "7iaL35Fs", "clock": {"initial": 180, "increment": 0, "totalTime": 180}}, {"id": "tGfdgFmK", "rated": true, "variant": "standard", "speed": "blitz", "perf": "blitz", "createdAt": 1774510502451, "lastMoveAt": 1774510621185, "status": "draw", "source": "arena", "players": {"white": {"user": {"name": "AdithyASreejitH", "flair": "smileys.alien", "id": "adithyasreejith"}, "rating": 2015, "ratingDiff": 7}, "black": {"user": {"name": "nuevo_repertorio", "id": "nuevo_repertorio"}, "rating": 2228, "ratingDiff": -3}}, "opening": {"eco": "A46", "name": "Yusupov-Rubinstein System", "ply": 5}, "moves": "d4 Nf6 Nf3 e6 e3 c5 b3 Nc6 Bb2 d5 Nbd2 b6 a3 Bb7 Bd3 Be7 O-O O-O Ne5 Rc8 f4 Nd7 Rf3 f6 Bxh7+ Kxh7 Rh3+ Kg8 Ng6 f5 Rh8+ Kf7 Qh5 Rxh8 Ne5+ Kg8 Qf7+ Kh7 Qh5+ Kg8 Qf7+ Kh7 Qh5+ Kg8", "clocks": [18003, 18003, 17883, 17683, 17795, 17619, 17611, 17411, 17227, 17043, 16987, 16955, 16675, 16883, 16299, 16787, 16059, 16691, 15939, 16195, 15843, 15611, 15427, 15491, 14387, 15139, 14155, 15083, 13939, 14267, 13483, 14147, 13331, 13715, 12563, 13635, 12427, 13555, 12347, 13499, 12299, 13419, 12267, 13372, 12266], "tournament": "7iaL35Fs", "clock": {"initial": 180, "increment": 0, "totalTime": 180}}, {"id": "UORSmsYJ", "rated": true, "variant": "standard", "speed": "blitz", "perf": "blitz", "createdAt": 1774097667501, "lastMoveAt": 1774097857324, "status": "resign", "source": "arena", "players": {"white": {"user": {"name": "SA_BOSS8855", "id": "sa_boss8855"}, "rating": 2029, "ratingDiff": 6}, "black": {"user": {"name": "AdithyASreejitH", "flair": "smileys.alien", "id": "adithyasreejith"}, "rating": 2029, "ratingDiff": -14}}, "winner": "white", "opening": {"eco": "B34", "name": "Sicilian Defense: Accelerated Dragon, Modern Variation", "ply": 9}, "moves": "e4 c5 Nf3 Nc6 d4 cxd4 Nxd4 g6 Nc3 Bg7 Be3 Nf6 h3 O-O Bc4 d6 a3 Bd7 O-O Rc8 Bb3 a6 f4 Qb6 Nf5 Qd8 Ng3 b5 Qf3 Na5 Ba2 Nc4 Bc1 e5 f5 Qb6+ Kh2 h5 Bg5 Nxb2 Nd5 Nxd5 Bxd5 Kh7 Nxh5 gxh5 Qxh5+ Kg8 f6 Be6 fxg7 Kxg7 Bf6+", "clocks": [18003, 9003, 17851, 8963, 17739, 8963, 17667, 8963, 17507, 8899, 17331, 8811, 17115, 8595, 16931, 8491, 16755, 8395, 16523, 8347, 16251, 7715, 16051, 7443, 15707, 6923, 15363, 5771, 14963, 5603, 14715, 5387, 14067, 5163, 13323, 4875, 12995, 4539, 10875, 3843, 10691, 3659, 10507, 2979, 9395, 2563, 9299, 2563, 8811, 1843, 8163, 1587, 7853, 1364], "tournament": "1lBTUQFu", "clock": {"initial": 180, "increment": 0, "totalTime": 180}}, {"id": "LEGRbSI4", "rated": true, "variant": "standard", "speed": "blitz", "perf": "blitz", "createdAt": 1774097529111, "lastMoveAt": 1774097662617, "status": "mate", "source": "arena", "players": {"white": {"user": {"name": "AdithyASreejitH", "flair": "smileys.alien", "id": "adithyasreejith"}, "rating": 2028, "ratingDiff": 1}, "black": {"user": {"name": "Akaza_DS", "id": "akaza_ds"}, "rating": 991, "ratingDiff": 0}}, "winner": "white", "opening": {"eco": "C23", "name": "Bishop's Opening", "ply": 3}, "moves": "e4 e5 Bc4 Nc6 Qh5 Qf6 Qf3 Bc5 Qf5 d6 Qxf6 Nxf6 Nf3 Nxe4 O-O Bg4 d3 Bxf3 gxf3 Ng5 Bxg5 f6 Be3 Bxe3 fxe3 O-O-O c3 a6 Be6+ Kb8 b4 Ne7 Bb3 d5 a4 f5 Na3 d4 exd4 exd4 c4 Ng6 b5 Nf4 c5 Nxd3 bxa6 bxa6 Bc4 Nb4 Rab1 a5 Nc2 Kc8 Nxb4 axb4 Rxb4 c6 Be6+ Kc7 Rfb1 Rde8 Rb7+ Kd8 Rd7+ Kc8 Re7+ Kd8 Rd7+ Kc8 Rxg7+ Kd8 Rb8#", "clocks": [9003, 9003, 8963, 8939, 8867, 8867, 8755, 8539, 8635, 8195, 8459, 8099, 8459, 7939, 8355, 7531, 8163, 7371, 8091, 6915, 7907, 6827, 7787, 6667, 7787, 6475, 7451, 6307, 7251, 6203, 7251, 6147, 7083, 6043, 6955, 5931, 6715, 5843, 6515, 5675, 6467, 5235, 6451, 5115, 6419, 4811, 6059, 4619, 5907, 4195, 5803, 4131, 5683, 3579, 5683, 3507, 5611, 3459, 5491, 3363, 5387, 3027, 5227, 2835, 5227, 2587, 5227, 2403, 5227, 2227, 5227, 2063, 5008], "tournament": "1lBTUQFu", "clock": {"initial": 180, "increment": 0, "totalTime": 180}}, {"id": "xOWxMC0N", "rated": true, "variant": "standard", "speed": "blitz", "perf": "blitz", "createdAt": 1772196720302, "lastMoveAt": 1772196831255, "status": "resign", "source": "arena", "players": {"white": {"user": {"name": "AdithyASreejitH", "flair": "smileys.alien", "id": "adithyasreejith"}, "rating": 2040, "ratingDiff": -12}, "black": {"user": {"name": "Leo_Mirana81", "id": "leo_mirana81"}, "rating": 2037, "ratingDiff": 6}}, "winner": "black", "opening": {"eco": "B03", "name": "Alekhine Defense: Exchange Variation", "ply": 9}, "moves": "e4 Nf6 e5 Nd5 c4 Nb6 d4 d6 exd6 cxd6 Nf3 g6 Be3 Bg7 Be2 O-O O-O Nc6 Nc3 Bg4 a3 Bxf3 Bxf3 Nxc4 Rc1 Rc8 Nb5 d5 b3 Nxe3 fxe3 a6 Nc3 e6 Na4 Qg5 Qd3 e5 dxe5 Nxe5 Qxd5 Qxe3+ Kh1 Rxc1", "clocks": [18003, 9003, 17619, 8923, 17507, 8835, 17507, 8771, 16915, 8771, 16739, 8715, 16627, 8715, 16579, 8667, 16507, 8619, 16419, 8531, 16219, 8395, 16115, 8291, 15435, 8107, 14971, 7667, 14331, 7539, 14283, 7395, 14083, 7355, 13259, 6739, 12875, 5707, 12627, 5579, 12411, 5467, 12299, 5381, 11856], "tournament": "dbHCGD2x", "clock": {"initial": 180, "increment": 0, "totalTime": 180}}, {"id": "hHiI7ln0", "rated": true, "variant": "standard", "speed": "blitz", "perf": "blitz", "createdAt": 1772196372270, "lastMoveAt": 1772196679674, "status": "outoftime", "source": "arena", "players": {"white": {"user": {"name": "IrPiran02", "id": "irpiran02"}, "rating": 1628, "ratingDiff": -1}, "black": {"user": {"name": "AdithyASreejitH", "flair": "smileys.alien", "id": "adithyasreejith"}, "rating": 2038, "ratingDiff": 2}}, "winner": "black", "opening": {"eco": "B34", "name": "Sicilian Defense: Accelerated Dragon, Exchange Variation", "ply": 9}, "moves": "e4 c5 Nf3 Nc6 d4 cxd4 Nxd4 g6 Nxc6 bxc6 Be3 Bg7 c3 Qc7 Qd2 Nf6 Bh6 Nxe4 Qe3 Bxh6 Qxh6 Qe5 Be2 Ba6 Bxa6 Ng3+ Kd1 Nxh1 Qe3 Qxe3 fxe3 Nf2+ Ke2 Ng4 h3 Nf6 Nd2 O-O Nf3 Rab8 b3 Nd5 Rc1 Rb6 Bd3 Nf6 c4 d5 c5 Rbb8 Rb1 a5 a3 Nd7 b4 e5 Ba6 Nxc5 Bd3 Nxd3 Kxd3 e4+ Ke2 exf3+ gxf3 axb4 axb4 Rb6 e4 Rfb8 Rc1 Rxb4 Rxc6 Rb2+ Ke3 dxe4 fxe4 R8b3+ Kf4 Rf2+ Kg5 Kg7 e5 Rxh3 Rc4 Rhf3 Rg4 Rf5+ Kh4 Rxe5 Kg3 Rff5 Ra4 Rh5 Kg4 Kh6 Ra3 Reg5+ Kf4 Rf5+ Kg4 f6 Ra7 Rhg5+ Kh3 Rf1 Kh2 Rf2+ Kh1 Rf4 Ra2 Rh4+ Rh2 Rxh2+ Kxh2 f5 Kh3 f4 Kh4 f3 Kh3 f2 Kh2 f1=N+ Kh3 Ne3 Kh4 Ng4 Kh3 Nf2+ Kh2 Rh5+ Kg3 Rg5+ Kxf2 Rf5+ Ke3 g5 Kd4 Kg6 Ke4 h5 Ke3 h4", "clocks": [18003, 9003, 17915, 9003, 17699, 8883, 17611, 8883, 17491, 8491, 17387, 8115, 17283, 7747, 17123, 7403, 16883, 6931, 16467, 6619, 16323, 6491, 15587, 5779, 15027, 4251, 13139, 4035, 11715, 3203, 11611, 3203, 11443, 3203, 11107, 3147, 10707, 2947, 10451, 2947, 10195, 2867, 9555, 2563, 9307, 2435, 9083, 2171, 8931, 1963, 8339, 1963, 8163, 1707, 7963, 1707, 7635, 1459, 6915, 1363, 6795, 1363, 6651, 1363, 6571, 1363, 6387, 1323, 6067, 1323, 5235, 1163, 5075, 1163, 4955, 1051, 4795, 1051, 4627, 955, 4259, 955, 3651, 714, 3267, 714, 3051, 714, 2955, 598, 2827, 598, 2595, 598, 2459, 598, 2243, 598, 2123, 598, 2019, 598, 1699, 598, 1531, 598, 1355, 598, 1203, 598, 930, 598, 766, 598, 687, 495, 589, 495, 513, 495, 490, 449, 490, 328, 490, 294, 482, 288, 430, 228, 430, 158, 331, 158, 303, 158, 248, 158, 224, 154, 131, 154, 51, 154, 0], "tournament": "dbHCGD2x", "clock": {"initial": 180, "increment": 0, "totalTime": 180}}, {"id": "UqVkQRFc", "rated": true, "variant": "standard", "speed": "blitz", "perf": "blitz", "createdAt": 1772196189273, "lastMoveAt": 1772196339434, "status": "mate", "source": "arena", "players": {"white": {"user": {"name": "AdithyASreejitH", "flair": "smileys.alien", "id": "adithyasreejith"}, "rating": 2036, "ratingDiff": 2}, "black": {"user": {"name": "WalterGoodman131", "id": "waltergoodman131"}, "rating": 1670, "ratingDiff": -1}}, "winner": "white", "opening": {"eco": "A45", "name": "Indian Defense", "ply": 2}, "moves": "d4 Nf6 Nc3 g6 e4 Bg7 e5 Ng8 f4 c5 d5 d6 Nf3 Qc7 Bd2 Bg4 Be2 Bxf3 Bxf3 dxe5 Qe2 exf4 d6 Qd7 O-O-O e5 Bxf4 Nf6 Qxe5+ Qe6 Qxe6+ fxe6 Bxb7 Nbd7 Bxa8 O-O Bc6 Nb6 Be5 Rd8 Rhf1 Nc4 Bxf6 Bxf6 Rxf6 Nxd6 Rxe6 Rf8 Rdxd6 h5 Nd1 Kh7 Rxg6 Rf1 Rh6+ Kg7 Rdg6+ Kf7 Bd5+ Ke7 Rh7+ Kd8 Rg8+ Rf8 Rxf8#", "clocks": [9003, 18003, 8971, 17963, 8827, 17907, 8771, 17595, 8619, 17539, 8347, 17315, 8251, 16987, 6363, 16883, 6059, 16555, 6059, 16427, 5411, 16195, 5307, 15715, 4731, 15475, 4387, 15331, 4099, 14907, 3947, 14803, 3859, 14555, 3819, 14475, 3699, 14227, 3299, 14131, 2611, 13955, 2267, 13835, 2267, 13715, 2099, 13371, 1955, 13323, 1835, 13323, 1747, 13115, 1747, 12971, 1739, 12891, 1715, 12787, 1643, 12651, 1515, 12179, 1514], "tournament": "dbHCGD2x", "clock": {"initial": 180, "increment": 0, "totalTime": 180}}, {"id": "HKFHz0l0", "rated": true, "variant": "standard", "speed": "blitz", "perf": "blitz", "createdAt": 1769261052757, "lastMoveAt": 1769261179113, "status": "resign", "source": "arena", "players": {"white": {"user": {"name": "BROOK-FC", "id": "brook-fc"}, "rating": 1984, "ratingDiff": 7}, "black": {"user": {"name": "AdithyASreejitH", "flair": "smileys.alien", "id": "adithyasreejith"}, "rating": 2044, "ratingDiff": -8}}, "winner": "white", "opening": {"eco": "B76", "name": "Sicilian Defense: Dragon Variation, Yugoslav Attack, Modern Line", "ply": 17}, "moves": "e4 c5 Nf3 Nc6 d4 cxd4 Nxd4 g6 Nc3 Bg7 Be3 Nf6 Qd2 O-O f3 d6 O-O-O Bd7 h4 h5 Be2 Rc8 Bh6 a6 Bxg7 Kxg7 g4 hxg4 fxg4 Rh8 h5 Bxg4 hxg6 fxg6 Bxg4 Nxd4 Bxc8 Nf3 Qf4", "clocks": [18003, 9003, 17787, 8963, 17699, 8963, 17635, 8939, 17523, 8867, 17467, 8739, 17315, 8355, 17235, 8355, 17091, 8315, 16947, 8107, 16603, 7947, 16187, 7403, 16035, 7243, 15939, 6891, 15795, 6027, 15387, 5763, 15091, 5579, 14579, 4899, 14083, 4643, 13077, 3410], "tournament": "itwpgYFU", "clock": {"initial": 180, "increment": 0, "totalTime": 180}}, {"id": "eaOjZ2vx", "rated": true, "variant": "standard", "speed": "blitz", "perf": "blitz", "createdAt": 1769260569416, "lastMoveAt": 1769260829319, "status": "mate", "source": "arena", "players": {"white": {"user": {"name": "Darsh96", "flair": "activity.lichess-berserk", "id": "darsh96"}, "rating": 2017, "ratingDiff": -5, "analysis": {"inaccuracy": 3, "mistake": 2, "blunder": 3, "acpl": 72}}, "black": {"user": {"name": "AdithyASreejitH", "flair": "smileys.alien", "id": "adithyasreejith"}, "rating": 2037, "ratingDiff": 7, "analysis": {"inaccuracy": 3, "mistake": 1, "blunder": 1, "acpl": 39}}}, "winner": "black", "opening": {"eco": "A16", "name": "English Opening: Anglo-Indian Defense, Queen's Knight Variation", "ply": 3}, "moves": "c4 Nf6 Nc3 d6 g3 Nbd7 Bg2 e5 e4 c6 Nge2 Be7 O-O O-O d4 exd4 Nxd4 Qc7 Nf5 Nb6 Nxe7+ Qxe7 b3 Bg4 Qd3 Be6 Bb2 Rfd8 Rad1 d5 cxd5 cxd5 exd5 Nfxd5 Nxd5 Nxd5 Bxd5 Rxd5 Qc3 f6 Rde1 Qf7 Rd1 Rad8 Rxd5 Bxd5 Rd1 Qe7 Qd4 b6 h4 Rd7 h5 Be6 Qe4 Rxd1+ Kh2 Bd5 Qxe7 Rh1#", "clocks": [18003, 18003, 17891, 17779, 17755, 17731, 17699, 17723, 17643, 17643, 17595, 17531, 17547, 17475, 17499, 17307, 17499, 17187, 17227, 16859, 16835, 16859, 16779, 16411, 16339, 16259, 16139, 15971, 15979, 15875, 15667, 15875, 14555, 15747, 14411, 15747, 14283, 15571, 12451, 15051, 10939, 14579, 9379, 14203, 9115, 14203, 8731, 13987, 8315, 12755, 7827, 11411, 7731, 10875, 2163, 10219, 2083, 10019, 1867, 9889], "analysis": [{"eval": 12}, {"eval": 14}, {"eval": 12}, {"eval": 49}, {"eval": 39}, {"eval": 55}, {"eval": 49}, {"eval": 44}, {"eval": 54}, {"eval": 62}, {"eval": 62}, {"eval": 61}, {"eval": 61}, {"eval": 65}, {"eval": 84}, {"eval": 121}, {"eval": 110}, {"eval": 161}, {"eval": 174}, {"eval": 201}, {"eval": 212}, {"eval": 218}, {"eval": 219}, {"eval": 232}, {"eval": 221}, {"eval": 293, "best": "e7d7", "variation": "Qd7 f3 Be6 Ba3 Rfd8 Rad1 Ne8 Qe3 Qc7 f4 a5 Ne2", "judgment": {"name": "Inaccuracy", "comment": "Inaccuracy. Qd7 was best."}}, {"eval": 226}, {"eval": 222}, {"eval": 225}, {"eval": 217}, {"eval": 218}, {"eval": 209}, {"eval": 104, "best": "e4e5", "variation": "e5", "judgment": {"name": "Inaccuracy", "comment": "Inaccuracy. e5 was best."}}, {"eval": 168, "best": "b6d5", "variation": "Nbxd5 Nxd5", "judgment": {"name": "Inaccuracy", "comment": "Inaccuracy. Nbxd5 was best."}}, {"eval": 76, "best": "d3d4", "variation": "Qd4", "judgment": {"name": "Inaccuracy", "comment": "Inaccuracy. Qd4 was best."}}, {"eval": 124}, {"eval": -16, "best": "d3b5", "variation": "Qb5", "judgment": {"name": "Mistake", "comment": "Mistake. Qb5 was best."}}, {"eval": -11}, {"eval": -24}, {"eval": -24}, {"eval": -106, "best": "d1d5", "variation": "Rxd5 Bxd5", "judgment": {"name": "Inaccuracy", "comment": "Inaccuracy. Rxd5 was best."}}, {"eval": -37, "best": "e7d7", "variation": "Qd7", "judgment": {"name": "Inaccuracy", "comment": "Inaccuracy. Qd7 was best."}}, {"eval": -37}, {"eval": -44}, {"eval": -48}, {"eval": -16}, {"eval": -41}, {"eval": -17}, {"eval": -473, "best": "c3a5", "variation": "Qa5 b6 Qc3 h5 Qe3 Bb7 Rxd8+ Qxd8 f3 Qd1+ Kf2 Kf7", "judgment": {"name": "Blunder", "comment": "Blunder. Qa5 was best."}}, {"eval": -16, "best": "e7e2", "variation": "Qe2 Qd3 Qxb2 a4 Qe5 a5 Kf7 h4 Rd7 a6 b5 Qxb5", "judgment": {"name": "Blunder", "comment": "Blunder. Qe2 was best."}}, {"eval": -170, "best": "d4e3", "variation": "Qe3", "judgment": {"name": "Mistake", "comment": "Mistake. Qe3 was best."}}, {"eval": -13, "best": "e7e2", "variation": "Qe2 Kh2 Kf7 Qd2 Qf3 Rg1 Re8 Qf4 Qxf4 gxf4 Re2 Bd4", "judgment": {"name": "Mistake", "comment": "Mistake. Qe2 was best."}}, {"eval": -544, "best": "d4e3", "variation": "Qe3 Kf7", "judgment": {"name": "Blunder", "comment": "Blunder. Qe3 was best."}}, {"eval": -543}, {"mate": -8, "best": "d4d7", "variation": "Qxd7 Bxd7 Ba3 Qxa3 Rxd7 Qc1+ Kh2 Qf1 f4 Qe2+ Kg1 Qxh5", "judgment": {"name": "Blunder", "comment": "Checkmate is now unavoidable. Qxd7 was best."}}, {"mate": -7}, {"mate": -7}, {"mate": -6}, {"mate": -1}], "tournament": "itwpgYFU", "clock": {"initial": 180, "increment": 0, "totalTime": 180}}, {"id": "m7yxIS88", "rated": true, "variant": "standard", "speed": "blitz", "perf": "blitz", "createdAt": 1769260335077, "lastMoveAt": 1769260541998, "status": "outoftime", "source": "arena", "players": {"white": {"user": {"name": "AdithyASreejitH", "flair": "smileys.alien", "id": "adithyasreejith"}, "rating": 2046, "ratingDiff": -9}, "black": {"user": {"name": "Pherryjamesbaloc", "flair": "nature.guide-dog", "id": "pherryjamesbaloc"}, "rating": 1974, "ratingDiff": 7}}, "winner": "black", "opening": {"eco": "A40", "name": "Queen's Pawn Game", "ply": 1}, "moves": "d4 c6 Nf3 d5 e3 Nf6 Bd3 Bg4 Nbd2 e6 c4 Nbd7 Qb3 Qc7 h3 Bh5 O-O Bd6 Qc2 O-O b3 Rac8 Bb2 Qa5 Bc3 Qd8 Bb2 Bb8 a3 Qc7 Ne5 Bg6 f4 Nxe5 fxe5 Nd7 Bxg6 fxg6 Qd3 Rf5 Qe2 Qa5 b4 Qb6 c5 Qd8 Qg4 Qf8 Nf3 Qf7 Ng5 Qe7 Nf3 Rcf8 Nd2 b6 a4 bxc5 bxc5 Nxc5 dxc5 Qxc5 Bd4 Qc2 Nf3 c5 Rac1 Qxa4 Bxc5 Qxg4 hxg4 Rxf3 gxf3 Rxf3 Rxf3 Bxe5 Rf2 h5 Rd2 hxg4 Bd4 Bg3 e4 dxe4 Bf2 Bf4 Re2 Bxc1 Rxe4 g3 Rg4 gxf2+ Kxf2 g5 Ra4 Bf4 Rxa7 Kh7 Kf3 Kg6 Kg4 Kf6 Ra6 g6 Rb6 Be5 Rd6 Bf4", "clocks": [9003, 9003, 8931, 9003, 8915, 8963, 8875, 8947, 8803, 8915, 8755, 8859, 8675, 8651, 8451, 8531, 8267, 8467, 8035, 8347, 7955, 8203, 7875, 8099, 7595, 7979, 7275, 7931, 7059, 7827, 6507, 7443, 6179, 7219, 5955, 7171, 5667, 7051, 5667, 6763, 5387, 6563, 5163, 6139, 4747, 6035, 4523, 5899, 3611, 5187, 3283, 4883, 3027, 4627, 2707, 4123, 2171, 3931, 2139, 3339, 2011, 3291, 1883, 2971, 1707, 2835, 1387, 2291, 1275, 2163, 1219, 1723, 1003, 1667, 823, 1667, 810, 1563, 769, 1451, 769, 1323, 595, 1219, 595, 1139, 390, 1067, 380, 940, 325, 847, 325, 787, 282, 736, 271, 725, 180, 725, 150, 719, 47, 719, 32, 612, 32, 582, 0], "tournament": "itwpgYFU", "clock": {"initial": 180, "increment": 0, "totalTime": 180}}, {"id": "Dv0qTJfx", "rated": true, "variant": "standard", "speed": "blitz", "perf": "blitz", "createdAt": 1769260086867, "lastMoveAt": 1769260301645, "status": "resign", "source": "arena", "players": {"white": {"user": {"name": "AdithyASreejitH", "flair": "smileys.alien", "id": "adithyasreejith"}, "rating": 2055, "ratingDiff": -9}, "black": {"user": {"name": "disideme", "id": "disideme"}, "rating": 1966, "ratingDiff": 8}}, "winner": "black", "opening": {"eco": "A45", "name": "Indian Defense: Reversed Chigorin Defense", "ply": 4}, "moves": "d4 Nf6 Nc3 c5 d5 d6 e4 a6 f4 Nbd7 Nf3 b5 e5 Ng8 Bd3 b4 Ne4 Nb6 e6 c4 Nfg5 fxe6 Qh5+ g6 Nf6+ exf6 Bxg6+ Ke7 Nf7 hxg6 Qxg6 Qe8 Nxh8 Qxg6 Nxg6+ Kf7 Nxf8 Kxf8 dxe6 Bxe6 h4 Bg4 Kf2 f5 Be3 Nd5 Bd2 Ngf6 c3 Ne4+ Ke1 Re8", "clocks": [18003, 18003, 17763, 17587, 17339, 17499, 17163, 17267, 17035, 16915, 16891, 16779, 16715, 16483, 16499, 16363, 16299, 16107, 15147, 15635, 14555, 14995, 13939, 14907, 12227, 13931, 12083, 13859, 11443, 13411, 11115, 12243, 10795, 12075, 10795, 12035, 10747, 11939, 10667, 11763, 10667, 10979, 10379, 10843, 9939, 10699, 8707, 10371, 7155, 10059, 6995, 9560, 6455], "tournament": "itwpgYFU", "clock": {"initial": 180, "increment": 0, "totalTime": 180}}, {"id": "5x90MQj3", "rated": true, "variant": "standard", "speed": "blitz", "perf": "blitz", "createdAt": 1769259887847, "lastMoveAt": 1769260052687, "status": "resign", "source": "arena", "players": {"white": {"user": {"name": "MuchumaIsaac", "flair": "smileys.smiling-face-with-sunglasses", "id": "muchumaisaac"}, "rating": 1846, "ratingDiff": -3}, "black": {"user": {"name": "AdithyASreejitH", "flair": "smileys.alien", "id": "adithyasreejith"}, "rating": 2051, "ratingDiff": 4}}, "winner": "black", "opening": {"eco": "A46", "name": "D\u00f6ry Defense", "ply": 4}, "moves": "Nf3 Nf6 d4 Ne4 Bf4 d5 e3 e6 Nbd2 f5 Nxe4 fxe4 Nd2 Bd6 Bg3 O-O c3 c5 Qg4 e5 Qh4 Qxh4 Bxh4 exd4 cxd4 cxd4 exd4 Nc6 Nb3 a5 Bb5 a4 Bxc6 bxc6 Nc5 Bxc5 dxc5 Ba6 b3 axb3 axb3 Rfb8 O-O-O Rxb3 Kc2 Rab8 Rb1 Bd3+", "clocks": [18003, 18003, 17915, 17715, 17755, 17611, 17667, 17507, 17611, 17403, 17483, 17211, 17403, 17011, 17267, 16851, 16819, 16419, 16507, 15603, 16355, 15019, 16251, 15019, 16051, 14979, 15955, 14947, 15467, 14779, 15267, 14363, 14987, 14043, 14499, 13795, 14419, 13755, 13411, 13347, 13243, 13251, 11763, 12627, 11347, 11835, 10747, 11572, 10267], "tournament": "itwpgYFU", "clock": {"initial": 180, "increment": 0, "totalTime": 180}}, {"id": "X1IudpNi", "rated": true, "variant": "standard", "speed": "blitz", "perf": "blitz", "createdAt": 1769259540526, "lastMoveAt": 1769259807151, "status": "mate", "source": "arena", "players": {"white": {"user": {"name": "Dgame007", "id": "dgame007"}, "rating": 1755, "ratingDiff": -2}, "black": {"user": {"name": "AdithyASreejitH", "flair": "smileys.alien", "id": "adithyasreejith"}, "rating": 2049, "ratingDiff": 2}}, "winner": "black", "opening": {"eco": "B30", "name": "Sicilian Defense: Old Sicilian", "ply": 4}, "moves": "e4 c5 Nf3 Nc6 d3 e6 Be2 d5 exd5 exd5 O-O Bd6 Re1 Nge7 Bg5 O-O Nc3 Be6 Nd2 a6 Bg4 Bxg4 Qxg4 f6 Bh6 Ng6 Bxg7 Kxg7 g3 d4 Nd5 Bxg3 Qe6 Be5 f4 Bxf4 Nxf4 Nxf4 Qg4+ Ng6 Ne4 f5 Qg3 fxe4 Rxe4 Re8 Rae1 Rxe4 Rxe4 Qf6 Qc7+ Qf7 Qb6 Rf8 h4 Qf2+ Kh1 Qf1+ Kh2 Rf2+ Kg3 Qg2#", "clocks": [18003, 18003, 17907, 17883, 17731, 17651, 17659, 17603, 17499, 17603, 17427, 17515, 17355, 17275, 17187, 16931, 16923, 16563, 16555, 16035, 16427, 15563, 16291, 15363, 15931, 14619, 15003, 14483, 13547, 13611, 12915, 12883, 11443, 11531, 9099, 10851, 8763, 10659, 8539, 10323, 8371, 10187, 6947, 10011, 6819, 9523, 6475, 9291, 6339, 9251, 5699, 8947, 4843, 8515, 3307, 8195, 3171, 8195, 3059, 8195, 2872, 8197], "tournament": "itwpgYFU", "clock": {"initial": 180, "increment": 0, "totalTime": 180}}, {"id": "HpVtMr7N", "rated": true, "variant": "standard", "speed": "blitz", "perf": "blitz", "createdAt": 1769259437547, "lastMoveAt": 1769259514606, "status": "resign", "source": "arena", "players": {"white": {"user": {"name": "AdithyASreejitH", "flair": "smileys.alien", "id": "adithyasreejith"}, "rating": 2043, "ratingDiff": 6}, "black": {"user": {"name": "pemujamu", "id": "pemujamu"}, "rating": 1962, "ratingDiff": -4}}, "winner": "white", "opening": {"eco": "D02", "name": "Queen's Pawn Game: Chigorin Variation", "ply": 4}, "moves": "d4 d5 Nf3 Nc6 e3 Nf6 Bd3 Bd7 Nbd2 e6 a3 Be7 b3 O-O Bb2 h6 Ne5 Nxe5 dxe5 Ne8 O-O f5 f4 c5 Rf3 b5 Rg3 Rf7 Qh5 Kh8 Qxf7", "clocks": [18003, 18003, 17955, 17875, 17923, 17699, 17795, 17603, 17747, 17387, 17595, 17267, 17555, 17171, 17515, 16947, 17403, 16675, 17187, 16179, 17051, 16043, 16963, 15699, 16747, 15571, 16499, 15451, 16259, 15131, 16105, 14670], "tournament": "itwpgYFU", "clock": {"initial": 180, "increment": 0, "totalTime": 180}}, {"id": "n03edXJu", "rated": true, "variant": "standard", "speed": "blitz", "perf": "blitz", "createdAt": 1769259206078, "lastMoveAt": 1769259418666, "status": "mate", "source": "arena", "players": {"white": {"user": {"name": "mahenb4u", "flair": "smileys.hugging-face", "id": "mahenb4u"}, "rating": 2007, "ratingDiff": -6}, "black": {"user": {"name": "AdithyASreejitH", "flair": "smileys.alien", "id": "adithyasreejith"}, "rating": 2035, "ratingDiff": 8}}, "winner": "black", "opening": {"eco": "B30", "name": "Sicilian Defense: Nyezhmetdinov-Rossolimo Attack", "ply": 5}, "moves": "e4 c5 Nf3 Nc6 Bb5 e6 Bxc6 bxc6 d3 d5 Nbd2 Bd6 e5 Be7 O-O Bf8 Ne1 Ne7 f4 Nf5 Ndf3 Be7 g3 h5 Kg2 Nh6 h3 Nf5 h4 Bd7 Bd2 Bc8 c3 Rh6 Ng5 f6 Ngf3 Rg6 exf6 Rxg3+ Kh2 Bxf6 Ng5 g6 Qe2 Rg4 Ng2 Ng3 Qe3 Nxf1+ Rxf1 Bxg5 fxg5 Qd6+ Kh1 Rg3 Qf2 Rh3+ Kg1 Qh2#", "clocks": [18003, 18003, 17883, 17683, 17771, 17307, 17683, 17131, 17683, 17019, 17683, 16723, 17443, 16515, 17443, 15963, 17331, 15787, 17275, 15643, 16939, 15307, 16539, 15147, 16131, 13947, 15643, 13379, 15227, 12499, 14523, 12195, 14187, 11627, 13987, 11523, 13251, 11203, 12179, 10987, 12027, 10931, 11851, 9891, 11275, 9715, 11051, 9291, 9963, 8963, 9923, 8803, 9651, 8691, 9427, 8027, 9187, 7827, 9110, 7744], "tournament": "itwpgYFU", "clock": {"initial": 180, "increment": 0, "totalTime": 180}}, {"id": "22q0kN8P", "rated": true, "variant": "standard", "speed": "blitz", "perf": "blitz", "createdAt": 1769256569522, "lastMoveAt": 1769256755709, "status": "resign", "source": "arena", "players": {"white": {"user": {"name": "AdithyASreejitH", "flair": "smileys.alien", "id": "adithyasreejith"}, "rating": 2045, "ratingDiff": -10}, "black": {"user": {"name": "mahenb4u", "flair": "smileys.hugging-face", "id": "mahenb4u"}, "rating": 1993, "ratingDiff": 7}}, "winner": "black", "opening": {"eco": "D01", "name": "Rapport-Jobava System, with e6", "ply": 5}, "moves": "d4 d5 Nc3 e6 Bf4 c6 e3 f5 Nf3 Nf6 Bd3 g6 Ne5 Bg7 Qe2 O-O h4 Bd7 O-O-O Be8 f3 Nbd7 g4 fxg4 fxg4 Nxe5 Bxe5 Qe7 h5 Nd7 Bxg7 Qxg7 hxg6 Bxg6 Bxg6 Qxg6 Qh2 Nf6 g5 Ne8 Rdg1 Ng7 Rg3 Rf5 Rh3 Raf8 Rxh7 Rf1+ Rxf1 Rxf1+ Kd2 Qxh7 Qb8+ Kf7 Qxb7+ Kg6 Qxc6 Qh2+ Kd3 Rf2 Nb1 Qg2 Qe8+ Nxe8", "clocks": [18003, 18003, 17771, 17947, 17707, 17859, 17603, 17755, 17507, 17699, 17307, 17643, 16987, 17579, 16731, 17491, 16523, 17323, 16299, 17235, 15979, 17139, 15651, 16803, 15467, 15803, 15203, 15171, 14971, 14859, 14731, 14811, 14595, 14691, 14307, 14587, 14203, 14451, 13979, 13707, 13771, 13635, 13539, 13523, 13323, 12643, 13051, 12523, 12387, 12411, 12371, 12259, 12251, 12107, 12115, 12067, 12043, 11899, 11547, 10211, 11083, 9619, 10811, 9151, 10524], "tournament": "itwpgYFU", "clock": {"initial": 180, "increment": 0, "totalTime": 180}}, {"id": "8OlJWV6q", "rated": true, "variant": "standard", "speed": "blitz", "perf": "blitz", "createdAt": 1769256179322, "lastMoveAt": 1769256480031, "status": "resign", "source": "arena", "players": {"white": {"user": {"name": "wadipadilla", "id": "wadipadilla"}, "rating": 1755, "ratingDiff": -2}, "black": {"user": {"name": "AdithyASreejitH", "flair": "smileys.alien", "id": "adithyasreejith"}, "rating": 2042, "ratingDiff": 3}}, "winner": "black", "opening": {"eco": "B30", "name": "Sicilian Defense: Old Sicilian", "ply": 4}, "moves": "e4 c5 Nf3 Nc6 Bc4 e6 Nc3 d6 a3 Nf6 d3 d5 exd5 exd5 Qe2+ Be7 Bb5 Bd7 Bxc6 Bxc6 O-O O-O Ne5 Bd6 Nxc6 bxc6 Nd1 Qc7 g3 Rae8 Ne3 d4 Nd5 Nxd5 Qf3 Nb6 b3 Re7 Bd2 Rfe8 Rae1 Rxe1 Rxe1 Rxe1+ Bxe1 Qe7 Bd2 Nd5 a4 h6 Qg4 Kh8 Qc8+ Kh7 Qxc6 Nf6 Qf3 Qe6 c3 dxc3 Bxc3 Nd5 Bb2 Nf6 d4 cxd4 Bxd4 Qe1+ Kg2 Qe4 Bxa7 Qxf3+ Kxf3 Kg6 h4 Kf5 g4+ Nxg4 Bd4 Ne5+ Bxe5 Kxe5 Kg4 Kd5 f4 Kc5 h5 Kb4 Kf5 Kxb3 a5 Kb4 a6 Bb8 Ke4 Kb5 a7 Bxa7 Kd5 Be3 Kd6 Bxf4+ Ke7 Be5 Kxf7 Bf6 Kg6 Kc5 Kf5 Kd5 Kg6 Ke5 Kf7 Kf5 Kg8 Kg5 Kf7 Kxh5", "clocks": [18003, 18003, 17939, 17955, 17811, 17955, 17379, 17723, 17251, 17571, 17083, 17467, 16963, 17467, 16387, 17227, 16227, 16779, 16035, 16411, 15867, 16163, 15731, 16043, 15595, 16043, 15395, 15811, 15155, 15595, 15059, 15467, 14683, 14883, 14491, 14467, 14139, 13339, 14043, 13187, 13787, 13051, 13699, 12899, 13611, 12811, 13403, 12699, 12619, 12347, 12323, 10643, 12043, 10347, 11915, 9547, 11027, 8707, 10787, 8411, 10659, 8283, 10035, 7371, 9547, 6819, 9331, 6771, 9155, 6771, 8539, 6459, 8459, 6339, 8075, 6171, 7979, 6019, 7627, 5731, 7491, 5619, 7355, 5443, 7235, 5339, 7147, 5211, 6955, 4955, 6955, 4603, 6915, 4427, 6803, 4291, 6707, 4251, 6683, 4059, 6683, 3907, 6683, 3699, 6579, 3699, 6467, 3699, 6395, 3699, 6331, 3667, 6251, 3667, 5851, 3667, 5755, 3667, 5548], "tournament": "itwpgYFU", "clock": {"initial": 180, "increment": 0, "totalTime": 180}}, {"id": "ImW1XNyK", "rated": true, "variant": "standard", "speed": "blitz", "perf": "blitz", "createdAt": 1769255892351, "lastMoveAt": 1769256160587, "status": "mate", "source": "arena", "players": {"white": {"user": {"name": "AdithyASreejitH", "flair": "smileys.alien", "id": "adithyasreejith"}, "rating": 2035, "ratingDiff": 7}, "black": {"user": {"name": "BROOK-FC", "id": "brook-fc"}, "rating": 1968, "ratingDiff": -5}}, "winner": "white", "opening": {"eco": "C68", "name": "Ruy Lopez: Exchange Variation", "ply": 7}, "moves": "e4 e5 Nf3 Nc6 Bb5 a6 Bxc6 dxc6 h3 Bd6 O-O Nf6 d4 exd4 e5 O-O exd6 cxd6 Qxd4 h6 Nc3 Re8 Bf4 d5 Rfe1 Bf5 Rxe8+ Qxe8 Re1 Qd7 Ne5 Qe6 Qd2 Ne4 Nxe4 dxe4 f3 exf3 Nxf3 Qxa2 Qc3 Qa4 Bg3 Bxc2 Re7 Rd8 Rxb7 Be4 Rb4 Qa1+ Kh2 Bd5 Rg4 g6 Nh4 Be6 Nxg6 Bxg4 Qh8#", "clocks": [18003, 18003, 17811, 17891, 17763, 17747, 17595, 17611, 17563, 17403, 17435, 17299, 17387, 17171, 17315, 16147, 16947, 15915, 16795, 14883, 16379, 14555, 15971, 14219, 15395, 14043, 14675, 14043, 14547, 13899, 14411, 13291, 14139, 12267, 13811, 12131, 13387, 11571, 13139, 10995, 12427, 10227, 11579, 9427, 10723, 6147, 10227, 5667, 9051, 5531, 8755, 5179, 8283, 4267, 7939, 4075, 7651, 3867, 7491], "tournament": "itwpgYFU", "clock": {"initial": 180, "increment": 0, "totalTime": 180}}, {"id": "kI53pAnt", "rated": true, "variant": "standard", "speed": "blitz", "perf": "blitz", "createdAt": 1769255615298, "lastMoveAt": 1769255858695, "status": "resign", "source": "arena", "players": {"white": {"user": {"name": "wadipadilla", "id": "wadipadilla"}, "rating": 1760, "ratingDiff": -2}, "black": {"user": {"name": "AdithyASreejitH", "flair": "smileys.alien", "id": "adithyasreejith"}, "rating": 2032, "ratingDiff": 3}}, "winner": "black", "opening": {"eco": "B88", "name": "Sicilian Defense: Sozin Attack, Leonhardt Variation", "ply": 12}, "moves": "e4 c5 Nf3 Nc6 Bc4 e6 Nc3 d6 d4 cxd4 Nxd4 Nf6 Nxc6 bxc6 Bg5 Be7 O-O d5 exd5 cxd5 Bb5+ Bd7 Bxf6 Bxf6 Bxd7+ Qxd7 Re1 O-O Ne2 Bxb2 Rb1 Rab8 c3 Ba3 Qc2 Bd6 g3 Qc7 Nf4 Bxf4 gxf4 Qxf4 Re3 Rfc8 Rg3 Qf5 Rxb8 Rxb8 Qd2 Qe4 f3 Rb1+ Kg2 Qe1 Qxe1 Rxe1 f4 Re2+ Kf3 Rxa2 Ke3 a5 h4 a4 Kd4 a3 c4 dxc4 Kxc4 Rb2 Rxa3 h6 Kd4 Rh2 Ra8+ Kh7 Rf8 Kg6 f5+ exf5 Ke5 Rxh4 Kd6 Re4 Kd5 h5 Rc8 h4 Rc2 Rg4 Ke5 Rg3 Rf2 h3 Rxf5 h2 Rf1 Rg1", "clocks": [18003, 18003, 17915, 17899, 17739, 17747, 17659, 17571, 17483, 17443, 17323, 17435, 17187, 17235, 16963, 16955, 16859, 16779, 16739, 16779, 16619, 16723, 16347, 16603, 16067, 16603, 15779, 16419, 15131, 16131, 15027, 16091, 14531, 15843, 14187, 15763, 13723, 15539, 13323, 15331, 13243, 15299, 13155, 14643, 12811, 13835, 12035, 13571, 11251, 12843, 10363, 12667, 10283, 12259, 10019, 12027, 9939, 11923, 9755, 11923, 9579, 11651, 9491, 11539, 9403, 11443, 9323, 11259, 9235, 11203, 8995, 11059, 8611, 10771, 8291, 10547, 8147, 10347, 7723, 10171, 7603, 9955, 7427, 9699, 7307, 9595, 6963, 9379, 6739, 9139, 6539, 8387, 6419, 8211, 6299, 8099, 6195, 8033, 5691], "tournament": "itwpgYFU", "clock": {"initial": 180, "increment": 0, "totalTime": 180}}, {"id": "aHclwKUx", "rated": true, "variant": "standard", "speed": "blitz", "perf": "blitz", "createdAt": 1769255551100, "lastMoveAt": 1769255581591, "status": "resign", "source": "arena", "players": {"white": {"user": {"name": "AdithyASreejitH", "flair": "smileys.alien", "id": "adithyasreejith"}, "rating": 2040, "ratingDiff": -8}, "black": {"user": {"name": "Chicalla_Francisco", "id": "chicalla_francisco"}, "rating": 2081, "ratingDiff": 5}}, "winner": "black", "opening": {"eco": "A48", "name": "East Indian Defense", "ply": 4}, "moves": "d4 Nf6 Nf3 g6 e3 Bg7 Nc3 O-O e4 d6 Bf4 c5 Qd2 cxd4 Nxd4 e5", "clocks": [18003, 18003, 17883, 17771, 17883, 17731, 17787, 17731, 17747, 17643, 17707, 17467, 17491, 17347, 16971, 17170, 16778], "tournament": "itwpgYFU", "clock": {"initial": 180, "increment": 0, "totalTime": 180}}, {"id": "1vYuDgMw", "rated": true, "variant": "standard", "speed": "blitz", "perf": "blitz", "createdAt": 1769255248437, "lastMoveAt": 1769255533353, "status": "mate", "source": "arena", "players": {"white": {"user": {"name": "AdithyASreejitH", "flair": "smileys.alien", "id": "adithyasreejith"}, "rating": 2057, "ratingDiff": -17}, "black": {"user": {"name": "Pasekaop", "id": "pasekaop"}, "rating": 1611, "ratingDiff": 11}}, "winner": "black", "opening": {"eco": "B27", "name": "Sicilian Defense: Hyperaccelerated Pterodactyl", "ply": 6}, "moves": "e4 c5 Nf3 g6 d4 Bg7 d5 Qa5+ c3 Nf6 e5 Ng4 Bf4 Qb6 Qb3 Qxb3 axb3 O-O h3 Nh6 Nbd2 Na6 Bxa6 bxa6 O-O e6 c4 Nf5 g4 Nd4 Nxd4 cxd4 Nf3 d3 Rad1 Rb8 Rxd3 exd5 cxd5 Rb4 Bd2 Rb5 Bc3 Rxb3 Nd2 Rb5 Nc4 Bb7 Nd6 Rb3 Ra1 Rb8 Nxb7 R8xb7 Rxa6 R3b6 Rxb6 Rxb6 Re3 Bh6 Kf1 Bxe3 fxe3 Kf8 Ke2 Ke8 Kd3 Ke7 Kc4 d6 exd6+ Kxd6 Bb4+ Ke5 Bc3+ Ke4 Bd4 Rb7 d6 Rd7 Bc5 Ke5 Kb5 Rxd6 Bxd6+ Kxd6 Ka6 Kd5 Kxa7 Kc4 e4 Kb3 e5 Kxb2 Kb7 Kc3 Kc7 Kd4 Kd7 Kxe5 Ke7 f6 Kf7 f5 Kg7 f4 Kxh7 Kf6 h4 f3 g5+ Kf5 Kh6 f2 h5 gxh5 g6 f1=Q g7 Qa6+ Kh7 Qb7 Kh8 Qxg7+ Kxg7 h4 Kf7 h3 Ke7 h2 Kd7 h1=Q Kd6 Qd1+ Ke7 Qe1+ Kf7 Qe6+ Kg7 Qf6+ Kh7 Kg5 Kg8 Kf5 Kh7 Ke6 Kg8 Qf7+ Kh8 Qf5 Kg8 Ke7 Kh8 Kf6 Kg8 Qg5+ Kh8 Qg7#", "clocks": [9003, 18003, 8859, 18003, 8755, 18003, 8483, 17875, 8139, 17579, 8003, 17155, 7947, 16691, 7331, 16027, 7099, 15827, 6875, 15691, 6667, 15435, 6307, 15307, 6259, 15203, 5899, 15011, 5667, 14579, 5419, 14579, 5331, 14419, 4923, 14355, 4731, 14035, 4539, 13779, 4291, 13403, 3699, 12851, 3227, 12587, 3035, 12291, 2867, 11883, 2531, 11459, 2411, 11259, 2355, 10451, 2099, 10355, 1995, 10211, 1947, 9979, 1947, 9635, 1947, 9563, 1939, 9475, 1939, 9379, 1747, 9283, 1651, 9131, 1531, 9035, 1451, 8627, 1315, 8451, 1275, 8267, 1235, 8019, 1235, 7971, 1187, 7971, 1147, 7907, 1043, 7907, 930, 7811, 930, 7667, 930, 7627, 930, 7475, 930, 7411, 886, 7339, 850, 7235, 719, 7083, 596, 7035, 471, 6891, 471, 6755, 471, 6611, 457, 6267, 457, 5995, 351, 5803, 351, 5539, 351, 5515, 335, 5499, 335, 5459, 335, 5379, 317, 5067, 317, 4875, 317, 4691, 317, 4459, 317, 3875, 317, 3771, 233, 3707, 233, 3515, 138, 2435, 138, 2291, 138, 2203, 77, 2091, 77, 1985], "tournament": "itwpgYFU", "clock": {"initial": 180, "increment": 0, "totalTime": 180}}, {"id": "byaCN3i0", "rated": true, "variant": "standard", "speed": "blitz", "perf": "blitz", "createdAt": 1769255074050, "lastMoveAt": 1769255238344, "status": "resign", "source": "arena", "players": {"white": {"user": {"name": "gornjak", "id": "gornjak"}, "rating": 1738, "ratingDiff": 9, "analysis": {"inaccuracy": 3, "mistake": 0, "blunder": 0, "acpl": 20}}, "black": {"user": {"name": "AdithyASreejitH", "flair": "smileys.alien", "id": "adithyasreejith"}, "rating": 2073, "ratingDiff": -16, "analysis": {"inaccuracy": 2, "mistake": 2, "blunder": 1, "acpl": 51}}}, "winner": "white", "opening": {"eco": "E10", "name": "Indian Defense: Anti-Nimzo-Indian", "ply": 5}, "moves": "Nf3 Nf6 c4 e6 d4 d5 b3 c5 e3 Nc6 cxd5 exd5 Nc3 cxd4 Nxd4 Bb4 Bd2 Nxd4 exd4 O-O Be2 Re8 O-O Bf5 Bf3 Qd6 Nb5 Qf8 Nc7 Bxd2 Qxd2 Rec8 Nxa8 Rxa8 Rac1 Rc8 Rxc8 Qxc8 Rc1 Qe8 Qc3 h6 Qc7 Kh7 Qxb7 Bc2 Bxd5 Nxd5 Qxd5 Qe2 Qf3 Qd2 Rf1 Bd3 Rd1 Qc2 Qxd3+", "clocks": [18003, 18003, 17835, 17867, 17635, 17827, 17555, 17275, 17451, 17035, 17219, 16763, 16643, 16571, 16507, 16395, 16275, 16251, 16139, 16171, 15947, 16003, 15731, 15915, 15451, 15027, 14995, 14395, 14555, 14195, 14235, 13819, 14003, 13819, 13827, 13539, 13619, 13539, 13451, 13163, 13331, 12811, 12675, 12315, 12515, 11891, 12099, 11459, 11923, 11371, 11451, 11155, 11163, 10931, 10755, 10339, 10660, 10125], "analysis": [{"eval": 10}, {"eval": 18}, {"eval": 12}, {"eval": 21}, {"eval": 11}, {"eval": 17}, {"eval": -19}, {"eval": -5}, {"eval": -34}, {"eval": -5}, {"eval": -26}, {"eval": -6}, {"eval": -76, "best": "c1b2", "variation": "Bb2 cxd4 Nxd4 Bb4+ Bc3 a5 a3 Bc5 Nxc6 bxc6", "judgment": {"name": "Inaccuracy", "comment": "Inaccuracy. Bb2 was best."}}, {"eval": -77}, {"eval": -76}, {"eval": -85}, {"eval": -81}, {"eval": -117}, {"eval": -117}, {"eval": -121}, {"eval": -131}, {"eval": -129}, {"eval": -138}, {"eval": -61, "best": "d8a5", "variation": "Qa5 Nb1 Bf5 Bxb4 Qxb4 Bf3 Rac8 Qd2 Qxd2 Nxd2 Rc2 Rfd1", "judgment": {"name": "Inaccuracy", "comment": "Inaccuracy. Qa5 was best."}}, {"eval": -137, "best": "a2a3", "variation": "a3 Bxc3", "judgment": {"name": "Inaccuracy", "comment": "Inaccuracy. a3 was best."}}, {"eval": -13, "best": "a8c8", "variation": "Rc8 Ne2 Bc2 Qe1 Ba3 Bc1 Bf8 Bg5 Qb6 Bxf6 Bb4 Qc1", "judgment": {"name": "Mistake", "comment": "Mistake. Rc8 was best."}}, {"eval": -9}, {"eval": 273, "best": "d6d7", "variation": "Qd7 Bxb4 Qxb5 Bd2 h6 Re1 Ne4 Bf4 Rac8 Bxe4 Bxe4 h3", "judgment": {"name": "Blunder", "comment": "Blunder. Qd7 was best."}}, {"eval": 181, "best": "d2b4", "variation": "Bxb4 Qxb4 Nc7 h6 Nxe8 Rxe8 Re1 Ne4 Rc1 Bd7 Re2 Qb6", "judgment": {"name": "Inaccuracy", "comment": "Inaccuracy. Bxb4 was best."}}, {"eval": 316, "best": "b4a3", "variation": "Ba3 Nxa8 Rxa8 Bc1 Bd6 Bg5 Ne4 Bxe4 dxe4 Bh4 Ba3 Qe2", "judgment": {"name": "Mistake", "comment": "Mistake. Ba3 was best."}}, {"eval": 299}, {"eval": 327}, {"eval": 309}, {"eval": 302}, {"eval": 313}, {"eval": 376}, {"eval": 371}, {"eval": 369}, {"eval": 377}, {"eval": 408}, {"eval": 377}, {"eval": 399}, {"eval": 373}, {"eval": 453}, {"eval": 458}, {"eval": 492}, {"eval": 466}, {"eval": 533}, {"eval": 530}, {"eval": 531}, {"eval": 548}, {"eval": 575}, {"eval": 513}, {"eval": 749, "best": "d2d4", "variation": "Qxd4 Qe2 Bg6 Rc1 a5 Rd1 Qh4 Kh1 a4 bxa4 Qxa4 f3", "judgment": {"name": "Inaccuracy", "comment": "Inaccuracy. Qxd4 was best."}}, {"eval": 730}, {"eval": 861}, {"eval": 849}], "tournament": "itwpgYFU", "clock": {"initial": 180, "increment": 0, "totalTime": 180}}, {"id": "sbV0dZgC", "rated": true, "variant": "standard", "speed": "blitz", "perf": "blitz", "createdAt": 1769254683315, "lastMoveAt": 1769254966206, "status": "mate", "source": "arena", "players": {"white": {"user": {"name": "Bolsonarochess", "id": "bolsonarochess"}, "rating": 1849, "ratingDiff": -3}, "black": {"user": {"name": "AdithyASreejitH", "flair": "smileys.alien", "id": "adithyasreejith"}, "rating": 2069, "ratingDiff": 4}}, "winner": "black", "opening": {"eco": "A45", "name": "Indian Defense", "ply": 2}, "moves": "d4 Nf6 c3 e6 e3 d5 f4 Bd6 Nf3 Ne4 Bd3 O-O O-O c5 b3 f5 Qe2 Nc6 Bb2 a6 Nbd2 b5 Rac1 c4 Bc2 a5 Nxe4 fxe4 Ne5 Bxe5 dxe5 Bd7 a3 cxb3 Bxb3 a4 Bc2 Na5 Rcd1 Nc4 Bc1 Qe7 g4 Nxa3 Bxa3 Qxa3 Qd2 Rfc8 Ra1 Qxc3 Qxc3 Rxc3 Bd1 Rxe3 f5 Rf8 f6 gxf6 exf6 Kf7 g5 Kg6 h4 h5 gxh6 Kxh6 f7 Rg3+ Kh2 Rg7 h5 Rgxf7 Rxf7 Rxf7 Bg4 Rf4 Kg3 Rf7 Rc1 Rg7 Kh4 a3 Rc7 Be8 Rc8 Ra7 Bxe6 a2 Bxd5 a1=Q Rxe8 Qf6+ Kg4 Qg5+ Kh3 Ra3+ Kh2 Qg3+ Kh1 Ra1#", "clocks": [18003, 18003, 17915, 17875, 17843, 17843, 17771, 17819, 17755, 17763, 17659, 17643, 17579, 16979, 17107, 16595, 16779, 16499, 16307, 16283, 16187, 16083, 16027, 15875, 15787, 15587, 15579, 15347, 15467, 15219, 15371, 15203, 14915, 14963, 14779, 14875, 14363, 14739, 14059, 14507, 13859, 14291, 13139, 14019, 13027, 13707, 12923, 13387, 12643, 13131, 12547, 13043, 12035, 12827, 11867, 12163, 11675, 11995, 11579, 11819, 11395, 11715, 11027, 11675, 10827, 11547, 10459, 10811, 10307, 10515, 8971, 10331, 8843, 10331, 8739, 10083, 8619, 9515, 8099, 9131, 7851, 8739, 7507, 8075, 6979, 7107, 6755, 6979, 6339, 6747, 6155, 6587, 5835, 6499, 5667, 6499, 5203, 6499, 5058, 6496], "tournament": "itwpgYFU", "clock": {"initial": 180, "increment": 0, "totalTime": 180}}, {"id": "O18Hn2El", "rated": true, "variant": "standard", "speed": "blitz", "perf": "blitz", "createdAt": 1769254290787, "lastMoveAt": 1769254654583, "status": "mate", "source": "arena", "players": {"white": {"user": {"name": "AdithyASreejitH", "flair": "smileys.alien", "id": "adithyasreejith"}, "rating": 2066, "ratingDiff": 3}, "black": {"user": {"name": "Trofy", "flair": "people.call-me-hand", "id": "trofy"}, "rating": 1745, "ratingDiff": -2}}, "winner": "white", "opening": {"eco": "B08", "name": "Pirc Defense: Classical Variation", "ply": 8}, "moves": "d4 Nf6 Nf3 g6 Nc3 Bg7 e4 d6 Bf4 Nbd7 Qd2 Nh5 Be3 O-O O-O-O e5 dxe5 Nxe5 Nxe5 Bxe5 Be2 Ng7 Bh6 Be6 Kb1 Qe8 h4 f5 exf5 Bxf5 Be3 Bxc3 Qxc3 Ne6 g4 Be4 Rhg1 Bc6 Bc4 Qe7 Bg5 Qd7 Rge1 d5 Qd2 dxc4 Qxd7 Bxd7 Rxd7 Nxg5 hxg5 Rxf2 Rxc7 Rg2 Rxc4 Rf8 a3 Rf7 Re8+ Kg7 Rcc8 Rg1+ Ka2 Rd7 Rg8+ Kf7 Rcf8+ Ke6 Rf6+ Ke5 Re8+ Kd5 Rc8 Rxg4 Ra8 a6 Rb6 Rxg5 Rb8 Rg2 c3 Re7 R6xb7 Rxb7 Rxb7 h5 Rh7 Rh2 Kb3 h4 Rg7 h3 Rxg6 Rh1 Rh6 h2 Kc2 Kc4 b3+ Kd5 Kb2 Ke4 c4 Kd4 a4 a5 Ka2 Kc3 Rh3+ Kb4 Rh5 Kc3 c5 Kd2 c6 Ke3 c7 Rc1 Rxh2 Rxc7 Rh5 Ra7 Ka3 Kd4 Rb5 Kc3 Rc5+ Kd4 b4 axb4+ Kxb4 Ra8 a5 Ra7 Rb5 Ra6 Rb6 Ra8 Kb5 Kd5 a6 Ra7 Rb7 Ra8 Kb6 Kd6 a7 Rc8 Rb8 Rc6+ Kb5 Rc7 a8=Q Rc5+ Kb4 Rc7 Rd8+ Ke6 Qa6+ Ke5 Qd6+ Ke4 Qd4+ Kf3 Rf8+ Ke2 Rf2+ Ke1 Qd2#", "clocks": [18003, 18003, 17803, 17899, 17443, 17827, 17435, 17643, 17387, 17499, 17251, 17339, 17043, 17067, 16843, 16771, 16667, 16555, 16403, 16555, 16171, 16315, 15787, 16099, 15443, 15851, 14923, 15731, 14187, 15419, 13763, 14843, 13507, 14627, 13259, 14419, 13019, 14179, 12651, 13987, 12291, 13771, 11851, 13499, 11435, 12931, 11243, 12931, 11051, 12699, 11003, 12363, 10963, 12171, 10715, 11867, 10411, 11715, 10107, 11611, 10019, 11123, 9811, 10987, 9547, 10891, 9483, 10771, 9403, 10603, 9003, 10403, 8731, 10139, 7475, 9971, 7091, 9691, 7035, 9435, 6755, 9411, 6579, 9123, 6579, 9067, 6395, 8699, 6307, 8603, 6147, 8395, 5995, 8339, 5875, 8339, 5563, 8107, 5171, 7979, 5091, 7891, 4963, 7747, 4787, 7531, 4507, 7315, 4355, 6987, 4091, 6891, 3931, 6739, 3747, 6683, 3499, 6443, 3459, 6299, 3451, 6123, 3283, 6027, 3179, 5795, 2827, 5579, 2795, 5379, 2795, 5115, 2403, 4891, 2187, 4675, 2187, 4467, 2115, 4371, 2067, 4195, 1939, 4123, 1899, 4051, 1755, 3699, 1595, 3291, 1555, 3187, 1395, 2915, 1195, 2827, 1131, 2587, 1075, 2395, 998, 2251, 942, 2251, 764, 2251, 664, 2075, 664], "tournament": "itwpgYFU", "clock": {"initial": 180, "increment": 0, "totalTime": 180}}, {"id": "VSArJL6k", "rated": true, "variant": "standard", "speed": "blitz", "perf": "blitz", "createdAt": 1769253881888, "lastMoveAt": 1769254260628, "status": "outoftime", "source": "arena", "players": {"white": {"user": {"name": "AKA73", "id": "aka73"}, "rating": 2113, "ratingDiff": -7}, "black": {"user": {"name": "AdithyASreejitH", "flair": "smileys.alien", "id": "adithyasreejith"}, "rating": 2055, "ratingDiff": 11}}, "winner": "black", "opening": {"eco": "A46", "name": "Indian Defense: Knights Variation", "ply": 3}, "moves": "d4 Nf6 Nf3 e6 g3 d5 Bg2 Ne4 O-O Bd6 c3 O-O Nbd2 f5 e3 Nd7 c4 c6 cxd5 exd5 Nxe4 fxe4 Nd2 Nf6 f3 exf3 Bxf3 Bh3 Bg2 Bxg2 Kxg2 Qd7 Qc2 Qe6 Qd3 Ne4 Nxe4 Rxf1 Kxf1 dxe4 Qb3 Rf8+ Kg2 Qf7 Qxf7+ Rxf7 Bd2 Kf8 Rd1 Ke7 Bc3 Ke6 b3 Kd5 Be1 b5 Rc1 Ba3 Rc2 Rb7 b4 Kd6 Rc5 Bb2 Re5 Re7 Rf5 Bc1 Kf2 Ke6 Re5+ Kf6 Rc5 Ba3 Rxc6+ Re6 Rc5 Rb6 Bc3 Ke6 d5+ Kd6 Ke2 Rb8 Kd2 Rb7 Kc2 a5 Kb3 axb4 Bxb4 Bxb4 Kxb4 Ra7 Rxb5 Rxa2 Kc4 Rxh2 Kd4 Rg2 Kxe4 Rxg3 Rb7 h5 Rb8 Rg4+ Kf3 Kxd5 Rh8 Rg5 Rh7 Ke5 Rh8 Rf5+", "clocks": [18003, 18003, 17915, 17939, 17875, 17251, 17875, 17171, 17739, 17131, 17651, 17027, 17435, 16971, 17299, 16683, 16979, 16483, 16579, 16043, 16443, 15739, 16443, 15579, 16307, 15059, 15875, 14987, 15515, 14731, 15515, 14635, 15027, 14099, 14659, 13899, 13899, 13787, 13763, 13459, 13235, 12587, 13035, 12235, 12827, 12235, 12611, 12131, 11963, 11715, 11851, 11539, 11475, 11355, 11043, 10923, 10875, 10355, 10747, 9515, 10619, 8611, 10395, 7907, 9771, 7291, 9387, 6923, 9267, 6435, 8075, 6091, 7915, 5331, 7691, 5115, 7235, 4891, 7067, 4507, 6763, 4323, 5763, 3651, 3931, 3539, 3579, 3419, 3427, 3267, 3427, 2939, 3427, 2827, 2443, 2667, 1979, 2515, 1787, 2379, 1331, 2323, 1115, 2011, 873, 1851, 723, 1795, 436, 1571, 295, 1331, 152, 1246, 0], "tournament": "itwpgYFU", "clock": {"initial": 180, "increment": 0, "totalTime": 180}}, {"id": "HMZOvPdv", "rated": true, "variant": "standard", "speed": "blitz", "perf": "blitz", "createdAt": 1769253813679, "lastMoveAt": 1769253866473, "status": "resign", "source": "arena", "players": {"white": {"user": {"name": "AdithyASreejitH", "flair": "smileys.alien", "id": "adithyasreejith"}, "rating": 2054, "ratingDiff": 1}, "black": {"user": {"name": "AaronkingChess2014", "flair": "activity.chess-pawn", "id": "aaronkingchess2014"}, "rating": 1539, "ratingDiff": 0}}, "winner": "white", "opening": {"eco": "A40", "name": "Englund Gambit", "ply": 2}, "moves": "d4 e5 dxe5 Bc5 Nf3 d6 exd6 Ne7 e3 cxd6 Bc4 Nd7 Ng5 O-O Qh5 h6 Nxf7 Kh7 Nxd8", "clocks": [9003, 18003, 9003, 17867, 8859, 17795, 8755, 17587, 8611, 17491, 8483, 17283, 8115, 16875, 7987, 16683, 7523, 15547, 7302, 15310], "tournament": "itwpgYFU", "clock": {"initial": 180, "increment": 0, "totalTime": 180}}, {"id": "FXdJ2Dde", "rated": true, "variant": "standard", "speed": "blitz", "perf": "blitz", "createdAt": 1769253480536, "lastMoveAt": 1769253796546, "status": "mate", "source": "arena", "players": {"white": {"user": {"name": "AdithyASreejitH", "flair": "smileys.alien", "id": "adithyasreejith"}, "rating": 2045, "ratingDiff": 9}, "black": {"user": {"name": "CheesekinG7273", "flair": "activity.trophy", "id": "cheeseking7273"}, "rating": 2004, "ratingDiff": -5}}, "winner": "white", "opening": {"eco": "D05", "name": "Queen's Pawn Game: Colle System", "ply": 7}, "moves": "d4 d5 Nf3 e6 e3 Nf6 Bd3 c5 Nbd2 cxd4 exd4 Nc6 b3 Bd6 a3 O-O Bb2 Re8 Ne5 Ne7 O-O Ng6 f4 b6 Rf3 Bb7 Rh3 Bxe5 fxe5 Ne4 Bxe4 dxe4 Qg4 Rc8 c4 Nxe5 Qh5 Ng6 Qxh7+ Kf8 Rf1 Qg5 Rg3 Qxd2 Qxg6 Re7 Bc3 Qh6 Qxh6 gxh6 Bb4 f5 Rh3 Ke8 Bxe7 Kxe7 Rxh6 Bc6 Rh7+ Kf6 Rxa7 b5 Ra6 bxc4 bxc4 Bb7 Rb6 Ba8 d5 Rxc4 Rxe6+ Kg5 Re5 Rd4 Rfxf5+ Kg6 Kf2 Rd2+ Kf1 Rd1+ Ke2 Rg1 Rg5+ Kf6 Ref5+ Ke7 Rg7+ Kd6 Rg6+ Kc5 d6+ Kc6 Rc5+ Kd7 Rc7+ Kd8 Rg8#", "clocks": [18003, 18003, 18003, 17931, 17963, 17851, 17923, 17747, 17867, 17627, 17835, 17579, 17795, 17379, 17739, 17339, 17707, 17275, 17571, 17043, 17403, 16987, 17339, 16491, 17123, 16195, 16499, 15995, 16283, 15939, 15715, 15939, 15579, 13987, 15331, 13067, 14643, 12251, 14491, 12203, 14267, 11795, 13851, 10763, 13691, 9675, 13331, 9163, 12379, 9163, 12283, 8707, 11707, 8107, 11411, 8107, 11259, 7683, 10923, 6803, 10923, 6635, 9987, 6315, 9811, 6195, 9547, 5915, 9403, 5515, 9267, 5347, 9067, 4619, 8691, 4435, 7971, 3595, 7283, 3235, 7075, 3059, 6571, 2907, 6483, 2691, 6435, 2539, 6331, 2443, 6211, 2099, 6107, 1139, 5899, 1126, 5794], "tournament": "itwpgYFU", "clock": {"initial": 180, "increment": 0, "totalTime": 180}}, {"id": "rlIkRm4K", "rated": true, "variant": "standard", "speed": "blitz", "perf": "blitz", "createdAt": 1769253242478, "lastMoveAt": 1769253461582, "status": "outoftime", "source": "arena", "players": {"white": {"user": {"name": "James1117", "flair": "smileys.smiling-face-with-sunglasses", "id": "james1117"}, "rating": 2114, "ratingDiff": -1}, "black": {"user": {"name": "AdithyASreejitH", "flair": "smileys.alien", "id": "adithyasreejith"}, "rating": 2043, "ratingDiff": 2}}, "opening": {"eco": "A01", "name": "Nimzo-Larsen Attack: Modern Variation", "ply": 2}, "moves": "b3 e5 Bb2 d6 Nf3 Nc6 d3 Bf5 e4 Bg6 Be2 f5 O-O fxe4 dxe4 Bxe4 Nbd2 Bg6 Re1 Nf6 Bc4 Be7 Be6 Bh5 Ne4 Nxe4 Rxe4 Bf7 Bxf7+ Kxf7 c4 Ke8 Qd5 Qd7 a3 Rf8 Rd1 Kd8 b4 a6 c5 Qf5 cxd6 cxd6 Bxe5 Nxe5 Rxe5 Qc2 Rde1 Rc8 Rxe7 Rc6 Qg5 Kc8 Qg4+ Kb8 Qd7 Rc7 Qxc7+ Qxc7 Rxc7 Kxc7 Re7+ Kc6 Rxg7 Re8 Kf1 Kd5 Rxh7 Kc6 Rh4 b6 Rd4 Kb5 Rxd6 a5 Nd4+ Ka4 bxa5 bxa5 Ra6 Kxa3 Rxa5+ Kb4 Rh5 Kc4 Nf3 Kc3 h4 Kc2 g3 Kb3 Kg2 Kb2 Rg5 Kc3 h5 Kd3 h6 Rh8 Rh5 Rh7 Ng5 Rh8 h7 Rxh7 Rxh7 Kd4 Re7 Kd3 Re3+ Kd4 Nf3+ Kd5", "clocks": [9003, 9003, 9003, 8563, 8923, 8491, 8843, 8219, 8675, 8011, 8675, 7683, 8675, 7563, 8675, 7499, 8251, 7043, 7875, 6811, 7771, 6579, 7451, 5979, 7203, 5763, 7083, 4907, 6883, 4907, 6699, 4723, 6435, 4675, 6187, 4635, 5939, 4387, 5539, 3827, 5403, 3427, 4995, 3427, 4451, 3275, 4371, 3075, 2787, 2763, 2387, 2379, 2099, 2179, 1987, 2051, 1915, 1987, 1795, 1939, 1755, 1899, 1691, 1859, 1643, 1811, 1515, 1739, 1435, 1579, 1355, 1547, 1307, 1507, 1195, 1387, 1083, 1267, 1011, 1147, 911, 1107, 779, 1107, 709, 1003, 672, 933, 617, 933, 556, 933, 556, 906, 549, 896, 540, 889, 500, 658, 500, 646, 391, 492, 356, 432, 263, 432, 251, 426, 177, 321, 97, 321, 0], "tournament": "itwpgYFU", "clock": {"initial": 180, "increment": 0, "totalTime": 180}}, {"id": "N4qdWNjE", "rated": true, "variant": "standard", "speed": "blitz", "perf": "blitz", "createdAt": 1769253104327, "lastMoveAt": 1769253211332, "status": "resign", "source": "arena", "players": {"white": {"user": {"name": "AdithyASreejitH", "flair": "smileys.alien", "id": "adithyasreejith"}, "rating": 2063, "ratingDiff": -20, "analysis": {"inaccuracy": 1, "mistake": 0, "blunder": 2, "acpl": 76}}, "black": {"user": {"name": "AaronkingChess2014", "flair": "activity.chess-pawn", "id": "aaronkingchess2014"}, "rating": 1529, "ratingDiff": 12, "analysis": {"inaccuracy": 3, "mistake": 0, "blunder": 0, "acpl": 27}}}, "winner": "black", "opening": {"eco": "A40", "name": "Englund Gambit", "ply": 2}, "moves": "d4 e5 dxe5 Bc5 Nf3 d6 exd6 Ne7 e3 cxd6 Bb5+ Bd7 Bxd7+ Nxd7 O-O O-O Nd4 Bxd4 Qxd4 Nf6 Nc3 Ng6 e4 Re8 Bg5 h6 Bxf6 Qxf6 Qxf6 gxf6 Nd5 Rec8 Nxf6+ Kg7 Nd5 Rxc2 Nc3 Rxb2 Rab1 Rxb1 Re1", "clocks": [9003, 18003, 8715, 17931, 8611, 17843, 8467, 17795, 8075, 17659, 7891, 17547, 7603, 17483, 7563, 17051, 7443, 16859, 7251, 16787, 6523, 16523, 6035, 16203, 5747, 15531, 5371, 15475, 5171, 15387, 5171, 14595, 4987, 14451, 4915, 14331, 4883, 13931, 4635, 13771, 4550, 13544], "analysis": [{"eval": 17}, {"eval": 113, "best": "g8f6", "variation": "Nf6 c4 e6 Nf3 d5 Nc3 Be7 Bf4 O-O e3", "judgment": {"name": "Inaccuracy", "comment": "Inaccuracy. Nf6 was best."}}, {"eval": 107}, {"eval": 177, "best": "b8c6", "variation": "Nc6 Nf3 d5 Bf4 Bc5 e3 Nge7 Nc3 O-O Qd2", "judgment": {"name": "Inaccuracy", "comment": "Inaccuracy. Nc6 was best."}}, {"eval": 125}, {"eval": 142}, {"eval": 132}, {"eval": 146}, {"eval": 138}, {"eval": 153}, {"eval": 106}, {"eval": 158}, {"eval": 153}, {"eval": 167}, {"eval": 203}, {"eval": 208}, {"eval": 146, "best": "b2b3", "variation": "b3", "judgment": {"name": "Inaccuracy", "comment": "Inaccuracy. b3 was best."}}, {"eval": 185}, {"eval": 170}, {"eval": 204}, {"eval": 181}, {"eval": 251, "best": "d6d5", "variation": "d5 Rd1 Qc7 b3 Nf5 Qd3 Qe5 Bb2 Nh4 g3 Nf3+ Kg2", "judgment": {"name": "Inaccuracy", "comment": "Inaccuracy. d5 was best."}}, {"eval": 242}, {"eval": 275}, {"eval": 307}, {"eval": 362}, {"eval": 373}, {"eval": 372}, {"eval": 367}, {"eval": 370}, {"eval": 366}, {"eval": 369}, {"eval": 337}, {"eval": 324}, {"eval": 277}, {"eval": 270}, {"eval": 43, "best": "a1b1", "variation": "Rab1 Re8 f3 Rec8 Ne3 Re2 Rfe1 Rd2 Kf1 Nf4 Red1 Re2", "judgment": {"name": "Blunder", "comment": "Blunder. Rab1 was best."}}, {"eval": 50}, {"eval": 37}, {"eval": 40}, {"mate": -1, "best": "f1b1", "variation": "Rxb1 Rc8", "judgment": {"name": "Blunder", "comment": "Checkmate is now unavoidable. Rxb1 was best."}}], "tournament": "itwpgYFU", "clock": {"initial": 180, "increment": 0, "totalTime": 180}}]